Workbook

Sheet Reference Matrix
A1: GENERAL INSTRUCTIONS
A2: This workbook contains twelve (12) worksheets to provide supplementary documentation to Annex 4.2. of the Administrative Order No. 25, series of 2011 Inter-Agency Task Force (AO25-IATF) Memorandum Circular No. 2023-1. Performance-Based Bonus (PBB) Focal Persons of State Universities and Colleges (SUCs) are requested to accomplish the appropriate and applicable worksheets. Please do not alter or edit the format of this template. Kindly input all requested information in each worksheet. Indicate the complete name of the institution in Row 1, and provide the links to respective Google Drive Folders in Row 7 of each worksheet. At the end of each worksheet, indicate the requested details of signatories. Kindly upload and submit the completed Summary Sheets (signed PDF and editable Excel file format) in the Government Executive Information System (GEIS) on or before 29 February 2024. The reference matrix below details the definition, formula, documentation, and means of verification for each Output and Outcome Indicator in the 2023 General Appropriations Act for SUCs. Thank you for your kind and usual cooperation.
A4: PROGRAM / INDICATOR | B4: INDICATOR | C4: DEFINITION | D4: FORMULA | E4: REFERENCES / GUIDES | F4: MEANS OF VERIFICATION
A5: HIGHER EDUCATION PROGRAM
A6: OUTCOME | B6: 1. Percentage of first-time licensure exam takers that pass the licensure exams | C6: Ratio of the passers to the total number of takers (1st time) of all board/licensure exams in FY 2023 | D6: Numerator: Total number of passers (1st time) of all board/licensure exams in FY 2023 Denominator: Total number of 1st time takers of all board/licensure exams in FY 2023 | E6: Summary Sheets | F6: 1. PRC/MARINA licensure examination results
A7: OUTCOME | B7: 2. Percentage of graduates (2 years prior) that are employed | C7: Ratio of graduates in FY 2021 who are employed as of FY 2023 to the total number of graduates in FY 2021 | D7: Numerator: Total number of graduates employed as of FY 2023 out of the graduates in FY 2021 (based on adopted Academic calendar) Denominator: Total number of graduates in FY 2021 in all undergraduate programs per campus (based on adopted academic calendar) | E7: Summary Sheets | F7: 1. Graduate tracer study 2. Result of survey of employed from the graduates in the 1st semester of FY 2021-2022, certified by the Registrar 3. Total Enrolment in the 1st Semester of AY 2021-2022, certified by the Registrar
A8: OUTPUT | B8: 1. Percentage of undergraduate students enrolled in CHED-identified and RDC-identified priority programs | C8: Ratio of undergraduate student enollment (1st Sem AY 2023-2024) in CHED identified and RDC-identified priority programs to all other programs | D8: Numerator: Number of students enrolled in CHED- identified and RDC-identified priority programs (1st Sem AY 2023-2024) Denominator: Total number of undergraduate enrollment (1st Sem AY 2023-2024) | E8: References in determining the disciplines/programs identified as priority offerings: a. CMO No. 5, s. 2019 b. CMO No. 10, s. 2021 c. CMO No. 7, s. 2023 d. RDC Resolutions | F8: 1. Duly certified enrollment report for the 1st Semester of AY 2023-2024 per campus 2. Summary of Enrolment by identified priority undergraduate programs, and all other programs per campus 3. CHED-identified priority programs listed in CHED Memorandum Order (CMO) No. 5, s. 2019 and CMO No. 10, s. 2021 4. For programs considered priority outside those identified by CHED, submit certification, resolution from RDC or similar Government Councils, etc.
A9: OUTPUT | B9: 2. Percentage of undergraduate programs with accreditation | C9: Ratio of undergraduate programs with valid accreditation (Level 1 - Level 4 as of December 31, 2023) to all accreditable programs | D9: Numerator: Number of undergraduate programs with Level 1-Level 4 accreditation valid as of December 31, 2023 Denominator: Total number of accreditable undergraduate programs as of December 31, 2023 | E9: Accreditation includes those issued by local and international bodies recognized by CHED; CMO No. 1, s. 2005; AACCUP (Level 1 - Level 4) | F9: 1. Accreditation Certificates 2. List of all undergraduate programs per campus with accreditation (include date of validity) or without accreditation (include reasons for non-accreditation), and indicate year of initial operation of each of the programs being offered
A10: ADVANCED EDUCATION PROGRAM
A11: OUTCOME | B11: 1. Percentage of graduate school faculty engaged in research work applied in any of the following: a) pursuing advanced research degree programs (doctorate degree) or b) actively pursuing within the last three (3) years (investigative research, basic and applied scientific research, policy research, social science research) or c) producing technologies for commercialization or livelihood improvement or d) whose research work resulted in an extension program | C11: Ratio of graduate school faculty engaged in research work to the total number of graduate school faculty. | D11: Numerator: Total number of graduate school faculty with plantilla positions engaged in research work (in any of the enumerated engagements) as of December 31, 2023 Denominator: Total number of graduate school faculty with plantilla positions as of December 31, 2023 | E11: Graduate school faculty: 1. List of graduate school faculty (full time or part time), with academic plantilla positions 2. Personnel Services index of plantilla positions (PSIPOP), with the name of graduate faculty listed in the PSIPOP as proof that faculty memeber can be considered in this indicator | F11: 1. Research work assignment, designations of the graduate school faculty 2. Any proof of involvement in (b) and/or (c) 3. Proof of registration/enrolment in an advance research degree for first year AY 2023-2024 4.List of graduate school faculty with plantilla engaged in research vs all graduate school faculty with plantilla position 5. Notarized MOA with partner community/ies and abstract or research work
A12: OUTPUT | B12: For State Universities: Percentage of graduate students enrolled in research degree programs | C12: Ratio of graduate student enollment (1st Sem AY 2022-2023) in research degree programs to total graduate school enrolment (1st sem AY 2022-2023) Research degree program refers to graduate programs with THESIS or DISSERTATION | D12: Numerator: Number of graduate students enrolled in research degree programs (1st Sem of AY 2023-2024) Denominator: Total number of graduate students enrollment in all graduate programs (1st Sem of AY 2023-2024) | E12: CMO No. 15, s. 2019 | F12: 1. Duly certified enrollment report 2. Summary of Enrolment by research and non-research degree program 3. Curriculum/Course Syllabi
A13: OUTPUT | B13: For State Colleges and Professional Institutes: Percentage of graduate students enrolled in CHED-identified or RDC-identified priority programs | C13: Ratio of graduate student enollment (1st Sem AY 2022-2023) in CHED identified and RDC-identified priority graduate programs to all other graduate programs | D13: Numerator: Graduate student enollment (1st Sem AY 2022-2023) in CHED identified and RDC-identified priority graduate programs Denominator: Total graduate student enollment (1st Sem AY 2022-2023) | E13: References in determining the disciplines/programs identified as priority offerings: a. CMO No. 5, s. 2019 b. CMO No. 10, s. 2021 c. CMO No. 7, s. 2023 d. RDC Resolutions | F13: 1. Duly certified enrollment report 2. Summary of Enrolment by identified priority graduate programs, and all other programs per campus 3. For programs considered priority outside those identified by the CHED, submit certification, resolution from RDC or similar Government Councils, etc.
A14: OUTPUT | B14: 2. Percentage of accredited graduate programs | C14: Ratio of graduate programs with valid accreditation (Level 1 - Level 4 as of December 31, 2023) to all accreditable programs | D14: Numerator: Number of graduate programs with Level 1-Level 4 accreditation valid as of December 31, 2023 Denominator: Total number of accreditable graduate programs as of December 31, 2023 | E14: Accreditation includes those issued by local and international bodies recognized by CHED; AACCUP (Level 1 - Level 4) | F14: 1. Accreditation Certificates 2. List of all graduate programs per campus with or without accreditation (include reasons for non-accreditation), indicate year of initial operation
A15: RESEARCH PROGRAM
A16: OUTCOME | B16: Number of research outputs in the last three years (FY 2021-2023) utilized by the industry or by other beneficiaries | C16: Number of research outputs from FY 2021-2023 utliized by industry or by other beneficiaries | D16: Number of research outputs from FY 2021-2023 utilized by industry or by other beneficiaries in FY 2023 | E16: Utilized by industry or other beneficiaries refers to the adopters/partners/communities, external to the institution | F16: 1. Proof that the research output was utilized by identified stakeholders/beneficiaries 2. MOAs/MOUs 3. Reports with testimonies 4. Certification from industries/beneficiaries on the utilization of research outputs
A17: OUTPUT | B17: 1. Number of research outputs completed within the year | C17: Refers to the total number of completed researches in FY 2023 | D17: Number of completed researches in FY 2023 | E17: Research outputs may comprise any or all of the following: 1. Completed research-based papers; 2. Research-based papers or articles published in journals or international refereed publications that are not in the Beall's List of Predatory Journals; 3. Research-based papers or articles presented in international, national, or regional fora or conferences; 4. Inventions or innovations, methods, composition, or processes as a result of research 5. Models/inventions duly patented and applied for commercial purposes or utilized/adopted for development/production/service provision | F17: 1. Abstracts of research outputs 2. Certificate of completion signed by the Research Director/Vice President for Research
A18: OUTPUT | B18: For State Universities: Percentage of researches published within the year (FY 2023) in internationally-refereed journal | C18: Refers to the ratio of research outputs published in FY 2023 to the total number of completed research outputs from FY 2021 to FY 2023 (to exclude completed research outputs published in 2021 and 2022) | D18: Numerator: Number of research outputs published within FY 2023 in internationally-refereed journal Denominator: Total number of completed research outputs from FY 2021 to FY 2023 (to exclude completed research outputs published in the prior years, 2021 and 2022) | E18: Beall's List of Predatory Journals Documentation on the details of journals to qualify in internationally refereed journals | F18: 1. Photocopy of the journal's title page, and 1st page of the article published
A19: OUTPUT | B19: For State Colleges and Professional Institutes: Percentage of researches presented within the year (FY 2023) in national, regional, and international fora | C19: Refers to the ratio of research outputs presented in FY 2023 to the total number of completed research outputs from FY 2021 to 2023 (to exclude research outputs already presented in 2021 and 2022) | D19: Numerator: Number of research outputs presented within FY 2023 in national, regional and international fora Denominator: Total number of completed research outputs from FY 2021-2023 (to exclude research outputs already presented prior to 2023) | E19: In-house review presentations are not included nor considered as presentations in qualified fora. | F19: 1. Conference proceeding indicating research article presented 2. Program of activities and attendance to the conference 3. Certificate of participation / recognition for presenting the research output
A20: TECHNICAL ADVISORY EXTENSION PROGRAM
A21: OUTCOME | B21: 1. Number of active partnerships with LGUs, industries, NGOs, NGAs, SMEs, and other stakeholders as a result of extension activities. | C21: Number partnerships established by the insitution with the industires, NGOs, NGAs, SMEs and other stakeholder group active as of December 31, 2023 | D21: Number of partnerships established as a result of extension activities | E21: Number partnerships established by the insitution with the industires, NGOs, NGAs, SMEs and other stakeholder group active as of December 31, 2023 | F21: 1. Proof of active partnerships 2. MOAs/MOUs 3. Reports with testimonies 4. Certifications
A22: OUTPUT | B22: 1. Number of trainees weighted by the length of training | C22: Refers to the insitution's total number of participants trained in relation to the corresponding length or duration of training | D22: Target number of trainees weighted by the length of training for FY 2023 | E22: Training hours are weighted as follows: < 8 hrs = 0.5 1 day (8 hours) = 1 2 days (16 hours) = 1.25 3-4 days (24-32 hours) = 1.5 5 days or more (40 hours or more) = 2 | F22: 1. Extension activity reports to include the attendance sheets, specifying the nature and duration of the training 2. Program of the Training Activity
A23: OUTPUT | B23: 2. Number of extension programs organized and supported consistent with the SUC's mandated and priority programs | C23: Refers to the number of extension programs organized by the SUC | D23: Target number of Extension Programs organized in FY 2023 | E23: Unit of analysis: Extension Programs Extension Program: (Reference: CMO 8 s.2010) Extension refers to the act of communicating and transferring knowledge and technology to specific sectors and target clienteles (as distinguished from those enrolled in formal degree programs and course offerings) to enable them to effectively improve production,community and/or institutions, and quality of life at the same time enhance the HEIs academic and research programs Integrated Extension Program SHALL include the following components: 1. Training programs 2. Technical assistance and advisory services 3. Communication/information services 4. Community outreach activities 5. Technology transfer and utilization | F23: 1. List of extension programs approved per mandated and priority programs 2. Program Description
A24: OUTPUT | B24: 3. Percentage of beneficiaries who rate the training course/s as satisfactory or higher in terms of quality and relevance | C24: Ratio of beneficiaries who rated the training course as satisfactory or higher than the total of number of beneficiaries | D24: Numerator: Number of beneficiaries who rated the training course(s) as satisfactory or higher Denominator: Total number of beneficiaries | E24: Rating Scale: 1 (P) = Poor 2 (F) = Fair 3 (S) = Satisfactory 4 (VS) = Very Satisfactory 5 (E) = Excellent | F24: 1. Survey questionnaire and samples of duly accomplished forms 2. Training program including attendance sheets 3. Summary of evaluation by beneficiaries
A25: CUSTODIAL CARE PROGRAM
A26: OUTCOME | B26: 1. Percentage of CCP resident-graduates employed within a year after graduation | C26: Ratio of graduates gainfully employed as of FY 2023 to the total number of CCP residents who graduated in AY 2022-2023 | D26: Numerator: Total number of CCP resident-graduates employed as of FY 2023 Denominator: Total number of CCP resident-graduates in AY 2022-2023 for all programs | F26: 1. Graduate tracer study 2. List/summary of CCP graduates of AY 2022-2023
A27: OUTPUT | B27: 1. Percentage of poor/disadvantaged students (CCP residents) served for non- academic needs | C27: Ratio of CCP students served for non-academic needs to the total number of students | D27: Numerator: Total number CCP students served for non-academic needs for FY 2023 Denominator: Total number of undergraduate students' enrollment for FY 2023 | F27: 1. List of CCP residents approved by management/board 2. Enrolment Report of CCP residents (1st Sem AY 2023-2024) 3. List/Summary of undergraduate enrollment (1st Sem AY 2023-2024)
A28: OUTPUT | B28: 2. Percentage of students (CCP residents) who graduated within the prescribed period | C28: Ratio of CCP students who finished their respective baccalaureate programs within the prescribed timeframe (graduates of 2nd Semester of AY 2022-2023) to the total number of CCP students who are enrolled since AY 2019-2020 | D28: Numerator: Total number of CCP students who graduated in 2nd Semester of AY 2020-2021 Denominator: Total number CCP students' First Year enrolment in the 1st Semester AY 2019-2020 | F28: 1. List of CCP residents enrolled in 1st year AY 2019-2020 2. List of CCP residents who graduated 2nd Sem of AY 2022-2023

Sheet Higher Education (Oc1)
B1: NAME OF INSTITUTION: | C1: (MARINDUQUE STATE COLLEGE)
B2: PROGRAM: | C2: HIGHER EDUCATION PROGRAM
B3: INDICATOR/S: | C3: Outcome Indicator 1: Percentage of first-time licensure exam takers that pass the licensure exams
B4: INSTRUCTIONS: | C4: Kindly fill out Column 1 by listing all undergraduate programs with licensure examination. Please do not abbreviate or shorten program names. In Column 2, list all examination dates for the corresponding programs and input in Column 3 and Column 4 the number of first time takers and first time passers respectively. In Column 5, provide the supporting documentation used in reference to the information in the previous columns. You may also provide links to the scanned copies for easier reference. Computations in the summary bar below is automated. To create additional rows, kindly insert new rows after Row 31.
B5: REFERENCES: | C5: ='Reference Matrix'!$E6 -> Summary Sheets
B6: MEANS OF VERIFICATION: | C6: ='Reference Matrix'!$F6 -> 1. PRC/MARINA licensure examination results
B7: LINK TO GOOGLE DRIVE FOLDER: | C7: (https://drive.google.com/drive/folders/1Zezs1rJYwXox2umra5r2TT9W34aBuL09?usp=drive_link)
A9: SAMPLE
A10: 1 | C10: 2 | D10: 3 | E10: 4 | F10: 5
A11: Undergraduate Program Offered | C11: Exam Date (MMM-YYYY) | D11: Number of 1st Time Takers | E11: Number of 1st Time Passers | F11: Supporting Documentation
A12: Main Campus, Quezon City, Manila
A13: 1 | B13: Bachelor in Secondary Education Major in English | C13: 44562 | D13: 83 | E13: 72 | F13: 1. PRC Official Results
A14: 2 | B14: Bachelor in Secondary Education Major in Mathematics | C14: 44562 | D14: 165 | E14: 159
A15: 3 | B15: Bachelor in Secondary Education Major in Science | C15: 44562 | D15: 134 | E15: 130
A16: 4 | B16: Bachelor of Science in Accountancy | C16: 44835 | D16: 223 | E16: 198
A17: 5 | B17: Bachelor of Science in Civil Engineering | C17: 44682 | D17: 321 | E17: 321
A19: 1 | C19: 2 | D19: 3 | E19: 4 | F19: 5
A20: Undergraduate Program Offered | C20: Exam Date (MMM-YYYY) | D20: Number of 1st Time Takers | E20: Number of 1st Time Passers | F20: Supporting Documentation
A21: Main Campus ( BOAC CAMPUS-Tanza, Boac, Marinduque)
A22: 1 | B22: Bachelor of Science in Nursing | C22: May & November 2023 | D22: 90 | E22: 86
A23: 2 | B23: Bachelor of Science in Social Work | C23: September 2023 | D23: 52 | E23: 37
A24: 3 | B24: Bacelor of Science in Electrical Engineering | C24: April & September 2023 | D24: 26 | E24: 20
A25: 4 | B25: Bachelor of Science in Electronics Engineering | C25: April & October 2023 | D25: 18 | E25: 5
A26: 5 | B26: Bachelor of Science in Civil Engineering | C26: April & November 2023 | D26: 119 | E26: 57
A27: 6 | B27: Bachelor of Science in Mechanical Engineering | C27: February & August 2023 | D27: 16 | E27: 15
A28: 7 | B28: Bachelor of Secondary Education | C28: March & September 2023 | D28: 101 | E28: 86
A29: 8 | B29: Bachelor of Elementary Education | C29: March & September 2023 | D29: 23 | E29: 23
A30: Campus 2 (GASAN CAMPUS-Banuyo, Gasan, Marinduque)
A31: 1 | B31: Bachelor of Science in Fisheries | C31: October 2023 | D31: 7 | E31: 4
A32: Campus 4 (TORRIJOS CAMPUS-Poctoy, Torrijos, Marinduque)
A33: 1 | B33: Bachelor of Science in Agriculture | C33: November 2023 | D33: 16 | E33: 11
C35: Total | D35: =SUM(D22:D33) -> 468 | E35: =SUM(E22:E33) -> 344
C36: PERCENTAGE | D36: =E35/D35 -> 0.73504274
A38: Prepared by:
B41: JANINE JOIE M. ROCHA | C41: 45348
B42: AAII, Office of the President for Academic Affairs | C42: Date
A45: Approved:
B48: Prof. DIOSDADO P. ZULUETA, DPA | C48: 45348
B49: SUC President III | C49: Date

Sheet Higher Education (Oc2)
A1: NAME OF INSTITUTION: | B1: ((MARINDUQUE STATE COLLEGE))
A2: PROGRAM: | B2: HIGHER EDUCATION PROGRAM
A3: INDICATOR/S: | B3: Outcome Indicator 2: Percentage of graduates (2 years prior) that are employed
A4: INSTRUCTIONS: | B4: In Column 1, in the campus header, input the name and address of each campus. List down the degree program for each graduate. In Column 2 and Column 3, list down all the 1st semester FY 2021-2022 graduates per degree program and then provide the status for each graduate. In Column 4, input the employment, business, or company of the graduate. For this purpose, Employment refers to any mode or form of employment regardless of status, including self-employment.
A5: REFERENCES: | B5: ='Reference Matrix'!$E7 -> Summary Sheets
A6: MEANS OF VERIFICATION: | B6: ='Reference Matrix'!$F7 -> 1. Graduate tracer study 2. Result of survey of employed from the graduates in the 1st semester of FY 2021-2022, certified by the Registrar 3. Total Enrolment in the 1st Semester of AY 2021-2022, certified by the Registrar
A7: LINK TO GOOGLE DRIVE FOLDER: | B7: (https://drive.google.com/drive/folders/1Zezs1rJYwXox2umra5r2TT9W34aBuL09?usp=drive_link)
A9: SAMPLE
A10: 1 | C10: 2 | D10: 3 | G10: 4 | H10: 5
A11: Program Name | C11: Name of Graduate | D11: Graduate Tracer Status (Employed, Unemployed, Not Tracked) | G11: Name of Employment / Business / Company | H11: Supporting Documentation
A12: Main Campus, Quezon City, Manila | H12: 1. Graduate Tracer Study 2. Official list of FY 2021 Graduates
A13: Bachelor in Secondary Education Major in Mathematics | B13: 1 | C13: Surname, First Name, MI. | D13: Employed | G13: Self-employed
A14: Bachelor in Secondary Education Major in Science | B14: 2 | C14: Surname, First Name, MI. | D14: Unemployed
A15: Bachelor in Secondary Education Major in Science | B15: 3 | C15: Surname, First Name, MI. | D15: Not Tracked
A16: Bachelor of Science in Accountancy | B16: 4 | C16: Surname, First Name, MI. | D16: Employed | G16: ABC Corporation
A17: Bachelor of Science in Accountancy | B17: 5 | C17: Surname, First Name, MI. | D17: Employed | G17: DEF & Company
A18: TOTAL NUMBER OF STUDENTS Main Campus, Quezon City, Manila | C18: =COUNTIFS($A13:$A17,"*",$C13:$C17,"*",$D13:$D17,"*") -> 5 | D18: E | E18: UE | F18: NT
D19: =COUNTIFS($A13:$A17,"*",$C13:$C17,"*",$D13:$D17, "Employed") -> 3 | E19: =COUNTIFS($A13:$A17,"*",$C13:$C17,"*",$D13:$D17, "Unemployed") -> 1 | F19: =COUNTIFS($A13:$A17,"*",$C13:$C17,"*",$D13:$D17, "Not Tracked") -> 1
A21: 1 | C21: 2 | D21: 3 | G21: 4 | H21: 5
A22: Program Name | C22: Name of Graduate | D22: Graduate Tracer Status (Employed, Unemployed, Not Tracked) | G22: Name of Employment / Business / Company | H22: Supporting Documentation
A23: Main Campus ( BOAC CAMPUS-Tanza, Boac, Marinduque)
A24: Bachelor of Science in Civil Engineering | B24: 1 | C24: LAZARTE, Eduardson C. | D24: Employed | G24: Sunwest Inc.
A25: Bachelor of Science in Civil Engineering | B25: 2 | C25: LIAO, Cyrill James S. | D25: Not Tracked
A26: Bachelor of Science in Civil Engineering | B26: 3 | C26: MADLA, Arvin Laurence | D26: Employed | G26: Cogee International Devt. Inc, Parañaque
A27: Bachelor of Science in Civil Engineering | B27: 4 | C27: MALING, John Robert S. | D27: Employed | G27: Rwsi/ Roof and Wall Saver Inc. (Paranaque)
A28: Bachelor of Science in Civil Engineering | B28: 5 | C28: MARANDA, John Kalvin M. | D28: Not Tracked
A29: Bachelor of Science in Civil Engineering | B29: 6 | C29: OSINSAO, Mary Ann D. | D29: Not Tracked
A30: Bachelor of Science in Civil Engineering | B30: 7 | C30: SADIWA, Jeric P. | D30: Unemployed
A31: Bachelor of Science in Civil Engineering | B31: 8 | C31: SERDEÑA, Marielle L. | D31: Not Tracked
A32: Three Year Assocciate in Civil Engineering | B32: 1 | C32: SAGUID, Rex T. | D32: Unemployed
A33: Two Year Computer Technician | B33: 1 | C33: SAGUID, Errelyn F. | D33: Employed | G33: Iqor / Dasmariñas Cavite
A34: Bachelor of Science in Mechanical Engineering | B34: 1 | C34: MUHI, Justine Jay R. | D34: Not Tracked
A35: Bachelor of Science in Mechanical Engineering | B35: 2 | C35: SARINO, Charles Henry M. | D35: Not Tracked
A36: BSED - Biological Sciences | B36: 1 | C36: ALEMAN, Mark Allen B. | D36: Employed | G36: EnfraUSA , Ortigas
A37: BSED - Biological Sciences | B37: 2 | C37: SOLIS, John Emerson O. | D37: Not Tracked
A38: BSED - Mathematics | B38: 1 | C38: PIZARRA, Ervinjon L. | D38: Employed | G38: St. Mary's College of Marinduque/ Isok Boac Marinduque
A39: BSED - Mathematics | B39: 2 | C39: REVILLA, Mark Neil A. | D39: Not Tracked
A40: BSED - Music Education | B40: 1 | C40: LABOG, Ricabelle M. | D40: Employed | G40: Department of Social Welfare and Development
A41: BSED - Music Education | B41: 2 | C41: LABOG, Rina C. | D41: Employed | G41: Marinduque Provincial Hospital/Santol, Boac, Marinduque
A42: BSED - Music Education | B42: 3 | C42: LANCION, Anna Karenina SJ. | D42: Employed | G42: Mary Help of Christians College - Salesian Sisters Inc.
A43: BSED - Music Education | B43: 4 | C43: MAMING, Erlainy R. | D43: Unemployed
A44: BSED - Music Education | B44: 5 | C44: MEDINA, JR., Joey M. | D44: Unemployed
A45: BSED - Music Education | B45: 6 | C45: QUITORIANO, Philip J. | D45: Employed | G45: Marinduque State College
A46: BSED - Major in MAPEH | B46: 1 | C46: DE CASTRO, Angelica R. | D46: Employed | G46: DepEd
A47: BSED - Major in MAPEH | B47: 2 | C47: JOGNO, Ella May J. | D47: Employed | G47: Sisters of Mary Of Bannuex, Inc. / Biga II, Silang, Cavite
A48: BSED - Major in MAPEH | B48: 3 | C48: ODIAS, Erika G. | D48: Not Tracked
A49: BSED - Major in MAPEH | B49: 4 | C49: PERALTA, Gerald Z. | D49: Employed | G49: Foundever - OJV Pasig City
A50: BSED - Major in MAPEH | B50: 5 | C50: QUIJANO, Essa R. | D50: Unemployed
A51: BSED - Major in MAPEH | B51: 6 | C51: SANCHEZ, Arjay L. | D51: Employed | G51: St. Mary's College of Marinduque
A52: BSED - Major in MAPEH | B52: 7 | C52: TULIAO, Richard S. | D52: Employed | G52: MSC BOAC MAIN CAMPUS
A53: BSED - Technology & Livelihood Education | B53: 1 | C53: AGUIRRE, Shyrose P. | D53: Unemployed
A54: BSED - Technology & Livelihood Education | B54: 2 | C54: ARNEDO, Jonalyn M. | D54: Employed | G54: Mercado, Boac, Marinduque
A55: BSED - Technology & Livelihood Education | B55: 3 | C55: CASTRO, Krystell Jean L. | D55: Employed | G55: Rusi MARINDUQUE - Brgy Sumangga Mogpog Marinduque
A56: BSED - Technology & Livelihood Education | B56: 4 | C56: DUNGSO, Mary Grace Z. | D56: Not Tracked
A57: BSED - Technology & Livelihood Education | B57: 5 | C57: GALANZA, Emalyn P. | D57: Employed | G57: DSWD MIMAROPA - 4Ps (Mogpog)
A58: BSED - Technology & Livelihood Education | B58: 6 | C58: HUERTA, Judy Ann K. | D58: Employed | G58: PSA
A59: BSED - Technology & Livelihood Education | B59: 7 | C59: LATORENA, Eriza Mae M. | D59: Not Tracked
A60: BSED - Technology & Livelihood Education | B60: 8 | C60: LAYLAY, Ruth Joy | D60: Employed | G60: MSC
A61: BSED - Technology & Livelihood Education | B61: 9 | C61: LUNAR, Jean M. | D61: Unemployed
A62: BSED - Technology & Livelihood Education | B62: 10 | C62: LUNAR, Rishelle V. | D62: Not Tracked
A63: BSED - Technology & Livelihood Education | B63: 11 | C63: MANGUBAT, Cristine O. | D63: Unemployed
A64: BSED - Technology & Livelihood Education | B64: 12 | C64: MANUBA, Jizelle M. | D64: Employed | G64: 2021-2022: Local Government Unit of Gasan
A65: BSED - Technology & Livelihood Education | B65: 13 | C65: MARILLANO, Mary Joy O. | D65: Unemployed
A66: BSED - Technology & Livelihood Education | B66: 14 | C66: MOCORRO, Myzanea F. | D66: Employed | G66: Ma'amZee Store
A67: BSED - Technology & Livelihood Education | B67: 15 | C67: NAZARENO, Ma. Caren M. | D67: Employed | G67: DepEd ALS
A68: BSED - Technology & Livelihood Education | B68: 16 | C68: OLIVEROS, Irene Mae V. | D68: Unemployed
A69: BSED - Technology & Livelihood Education | B69: 17 | C69: PALOMARES, Bernajane R. | D69: Employed | G69: Technological Institute of the Philippines - Quezon City
A70: BSED - Technology & Livelihood Education | B70: 18 | C70: PERLAS, Maryjane L. | D70: Not Tracked
A71: BSED - Technology & Livelihood Education | B71: 19 | C71: PERLAS, Nichelle | D71: Unemployed
A72: BSED - Technology & Livelihood Education | B72: 20 | C72: PIANO, Jeneses M. | D72: Employed | G72: BUREAU OF JAIL MANAGEMENT AND PENOLOGY BATANGAS CITY
A73: BSED - Technology & Livelihood Education | B73: 21 | C73: RODELAS, Aurora Malaya P. | D73: Not Tracked
A74: BSED - Technology & Livelihood Education | B74: 22 | C74: SAGUID, Aireen C. | D74: Employed | G74: Makabata School Foundation -
A75: BSED - Technology & Livelihood Education | B75: 23 | C75: SAGUID, Krisel R. | D75: Employed | G75: Acadsoc, Lucena city
A76: Bachelor of Public Administration | B76: 24 | C76: ZOLETA, Rica S. | D76: Employed | G76: Marinduque Technical and Vocational Institute
A77: Bachelor of Public Administration | B77: 1 | C77: GILBOY, Gerald C. | D77: Employed | G77: Cook, Restaurant at Gasan Marinduque
A78: Bachelor of Public Administration | B78: 2 | C78: GUEVARA, Rochille E. | D78: Employed | G78: Gil J. Puyat Ave., Makati 1200 Metro Manila
A79: Bachelor of Public Administration | B79: 3 | C79: SALAZAR, Rizza Mae P. | D79: Employed | G79: Double-D Global Solutions, Inc. / No. 14 Sgt. Esguerra Avenue, Brgy. South Triangle, Quezon City
A80: Bachelor of Public Administration | B80: 4 | C80: SIGUE, Edmalyn L. | D80: Not Tracked
A81: BS - Law EnforcementAdministration | B81: 5 | C81: TOLENTINO, Deziree S. | D81: Employed | G81: CLAIMS PROCESSOR PHILIPPINES INC. - Gil Puyat Makati
A82: BS - Law EnforcementAdministration | B82: 1 | C82: AGUIRRE, Sandrix P. | D82: Unemployed
A83: BS - Law EnforcementAdministration | B83: 2 | C83: CAPUCAO, Charwin S. | D83: Employed | G83: Grocery Store Personnel ; Cavite
A84: BS - Law EnforcementAdministration | B84: 3 | C84: ESPLANA, Mary Grace L. | D84: Employed | G84: PENRO-MARINDUQUE (DENR) - Bangbangalon Boac, Marinduque
A85: BS - Law EnforcementAdministration | B85: 4 | C85: LACDAO, John Warrey T. | D85: Employed | G85: SONICOM SECURITY AGENCY CO. - #0507 Dagohoy St. Brgy. Poblacion, San jose Occidental Mindoro
A86: BS - Law EnforcementAdministration | B86: 5 | C86: LADA, Ellaine R. | D86: Unemployed
A87: BS - Law EnforcementAdministration | B87: 6 | C87: LIMPIADO, Mark Angelo DG. | D87: Unemployed
A88: BS - Law EnforcementAdministration | B88: 7 | C88: LOTO, Rico L. | D88: Not Tracked
A89: BS - Law EnforcementAdministration | B89: 8 | C89: MAGCULANG, Mc Nel A. | D89: Employed | G89: ALFA Co.
A90: BS - Law EnforcementAdministration | B90: 9 | C90: MALCO, Earl John Q. | D90: Employed | G90: Aggreko Energy Rental Solution Inc.
A91: BS - Law EnforcementAdministration | B91: 10 | C91: MANALO, Fernan F. | D91: Unemployed
A92: BS - Law EnforcementAdministration | B92: 11 | C92: MANDIA, John Laurence DLS. | D92: Not Tracked
A93: BS - Law EnforcementAdministration | B93: 12 | C93: MARQUEZ, Francis L. | D93: Unemployed
A94: BS - Law EnforcementAdministration | B94: 13 | C94: MARTIZANA, Junan N. | D94: Unemployed
A95: BS - Law EnforcementAdministration | B95: 14 | C95: MASALAYSAY, Leo Mar L. | D95: Employed | G95: Gasan MPS
A96: BS - Law EnforcementAdministration | B96: 15 | C96: MASCARIÑAS, Arbin F. | D96: Not Tracked
A97: BS - Law EnforcementAdministration | B97: 16 | C97: MATRE, Renier Sherwin M. | D97: Not Tracked
A98: BS - Law EnforcementAdministration | B98: 17 | C98: MEJARITO, Jake Steven O. | D98: Employed | G98: DJA Security Services INC. - Pasay City
A99: BS - Law EnforcementAdministration | B99: 18 | C99: MELENDEREZ, Jeaza C. | D99: Unemployed
A100: BS - Law EnforcementAdministration | B100: 19 | C100: METIN, Renneil M. | D100: Employed | G100: Sunwest Corporation
A101: BS - Law EnforcementAdministration | B101: 20 | C101: MERENCILLO, Jestoni N. | D101: Not Tracked
A102: BS - Law EnforcementAdministration | B102: 21 | C102: ORLANDA, Gerald Jake N. | D102: Not Tracked
...

Sheet Higher Education (Op1)
B1: NAME OF INSTITUTION: | C1: (MARINDUQUE STATE COLLEGE)
B2: PROGRAM: | C2: HIGHER EDUCATION PROGRAM
B3: INDICATOR/S: | C3: Output Indicator 1: Percentage of undergraduate students enrolled in CHED-identified and RDC-identified priority programs
B4: INSTRUCTIONS: | C4: Kindly fill out Column 1 by listing all undergraduate programs offered in each campus. Please do not abbreviate or shorten program names. In Column 2, identify if the program offered is a priority program using the references listed below. Input the number of enrollees for each corresponding program. In Column 3, list down the documents submitted to verify the information provided in the previous columns. You may provide links to the electronic copies of supporting documents in this column.
B5: REFERENCES: | C5: ='Reference Matrix'!$E8 -> References in determining the disciplines/programs identified as priority offerings: a. CMO No. 5, s. 2019 b. CMO No. 10, s. 2021 c. CMO No. 7, s. 2023 d. RDC Resolutions
B6: MEANS OF VERIFICATION: | C6: ='Reference Matrix'!$F8 -> 1. Duly certified enrollment report for the 1st Semester of AY 2023-2024 per campus 2. Summary of Enrolment by identified priority undergraduate programs, and all other programs per campus 3. CHED-identified priority programs listed in CHED Memorandum Order (CMO) No. 5, s. 2019 and CMO No. 10, s. 2021 4. For programs considered priority outside those identified by CHED, submit certification, resolution from RDC or similar Government Councils, etc.
B7: LINK TO GOOGLE DRIVE FOLDER: | C7: (https://drive.google.com/drive/folders/1Zezs1rJYwXox2umra5r2TT9W34aBuL09?usp=drive_link)
A9: SAMPLE
A10: 1 | C10: 2 | E10: 3
A11: Undergraduate Program Offered | C11: No. of Enrollees for 1st Semester AY 2023-2024 | E11: Supporting Documentation
C12: Priority Program | D12: Non-Priority Program
A13: Main Campus, Quezon City, Manila | E13: 1. Certified Enrollment Report for 1st Semester AY 2023-2024 2. CHED Memorandum Order No. 10, s. 2021
A14: 1 | B14: Bachelor in Secondary Education Major in English | D14: 85
A15: 2 | B15: Bachelor in Secondary Education Major in Mathematics | C15: 165
A16: 3 | B16: Bachelor in Secondary Education Major in Science | C16: 134
A17: 4 | B17: Bachelor of Arts in Social Sciences | C17: 199
A18: 5 | B18: Bachelor of Science in Accountancy | C18: 223
A19: 6 | B19: Bachelor of Science in Civil Engineering | C19: 321
A21: 1 | C21: 2 | E21: 3
A22: Undergraduate Program Offered | C22: No. of Enrollees for 1st Semester AY 2023-2024 | E22: Supporting Documentation
C23: Priority Program | D23: Non-Priority Program
A24: Boac Main Campus-Tanza, Boac, Marinduque
A25: 1 | B25: Bachelor of Science in Civil Engineering | C25: 431
A26: 2 | B26: Bachelor of Science in Computer Engineering | C26: 144
A27: 3 | B27: Bachelor of Science in Electrical Engineering | C27: 161
A28: 4 | B28: Bachelor of Science in Electronics Engineering | C28: 94
A29: 5 | B29: Bachelor of Science in Mechanical Engineering | C29: 161
A30: 6 | B30: Bachelor of Science in Industrial Technology | C30: 1673
A31: 7 | B31: Bachelor of Science in Information Technology | C31: 729
A32: 8 | B32: Bachelor of Science in Information System | C32: 248
A33: 9 | B33: Bachelor of Secondary Education | C33: 306
A34: 10 | B34: Bachelor of Culture and Arts Education | C34: 103
A35: 11 | B35: Bachelor of Technology and Livelihood Education | C35: 103
A36: 12 | B36: Bachelor of Arts in English Language Studies | D36: 162
A37: 13 | B37: Bachelor of Arts in Communication | C37: 233
A38: 14 | B38: Bachelor of Science in Social Works | C38: 280
A39: 15 | B39: Bachelor of Science in Entrepreneurship-Entrepreneurial Management | C39: 248
A40: 16 | B40: Bachelor of Science in Business Administration | C40: 855
A41: 17 | B41: Bachelor of Science in Accountancy | C41: 103
A42: 18 | B42: Bachelor of Science in Law Enforcement Administration | D42: 290
A43: 19 | B43: Bachelor of Science in Public Administration | D43: 304
A44: 20 | B44: Bachelor of Science in Environmental Science | C44: 200
A45: 21 | B45: Bachelor of Science in Nursing | C45: 428
A46: 22 | B46: Bachelor of Science in Midwifery | C46: 65
A47: 23 | B47: Diploma in Midwifery
A48: GASAN CAMPUS-Pinggan, Gasan, Marinduque
A49: 1 | B49: Bachelor of Science in Fisheries | C49: 393
A50: STA. CRUZ CAMPUS-Matalaba, Sta. Cruz, Marinduque
A51: 1 | B51: Bachelor of Elementary Education | C51: 121
A52: 2 | B52: Bachelor of Arts in Political Science | D52: 222
A53: 3 | B53: Bachelor of Science in Accounting Information System | C53: 98
A54: 4 | B54: Bachelor of Science in Tourism Management | C54: 399
A55: 5 | B55: Bachelor of Science in Information System | C55: 145
A56: TORRIJOS CAMPUS-Poctoy, Torrijos, Marinduque
A57: 1 | B57: Bachelor of Science in Agriculture | D57: 145
A58: 2 | B58: Bachelor in Agricultural Technology | C58: 96
A59: 3 | B59: Bachelor of Science in Entrepreneurship-Agri-Business | C59: 1
A60: 4 | B60: Diploma in Agricultural Technology
A61: 5 | B61: Certificate in Agricultural Science
B63: Sub Total | C63: =SUM(C25:C62) -> 7818 | D63: =SUM(D25:D62) -> 1123
B64: Total Number of Enrollees | C64: =SUM(C63:D63) -> 8941
B65: PERCENTAGE | C65: =C63/C64 -> 0.87439884
A67: Prepared by:
B70: GEMMA A. TIROL | C70: 45348
B71: College Registrar | C71: Date
A74: Approved:
B77: Prof. DIOSDADO P. ZULUETA, DPA | C77: 45348
B78: SUC President III | C78: Date

Sheet Higher Education (Op2)
B1: NAME OF INSTITUTION: | C1: (MARINDUQUE STATE COLLEGE)
B2: PROGRAM: | C2: HIGHER EDUCATION PROGRAM
B3: INDICATOR/S: | C3: Output Indicator 2: Percentage of undergraduate programs with accreditation
B4: INSTRUCTIONS: | C4: In Column 1, list down all undergraduate degree programs offered by the institution. Input the Year of Initial Operation of each degree program in Column 2. In Column 3, select the Program Accreditation Status of each program from the dropdown menu. In Column 4, provide the Validity of Accreditation of each program. Refer to the issued accreditation certificate. Provide descriptions and links to supporting documentation in Column 5.
B5: REFERENCES: | C5: ='Reference Matrix'!$E9 -> Accreditation includes those issued by local and international bodies recognized by CHED; CMO No. 1, s. 2005; AACCUP (Level 1 - Level 4)
B6: MEANS OF VERIFICATION: | C6: ='Reference Matrix'!$F9 -> 1. Accreditation Certificates 2. List of all undergraduate programs per campus with accreditation (include date of validity) or without accreditation (include reasons for non-accreditation), and indicate year of initial operation of each of the programs being offered
B7: LINK TO GOOGLE DRIVE FOLDER: | C7: (https://drive.google.com/drive/folders/1Zezs1rJYwXox2umra5r2TT9W34aBuL09?usp=drive_link)
A9: SAMPLE
A10: 1 | C10: 2 | D10: 3 | E10: 4 | G10: 5
A11: Undergraduate Programs Offered | C11: Year of Initial Operation | D11: Program Accreditation Status | E11: Validity of Accreditation (Ref. Accreditation Certificate) | G11: Supporting Documentation / Reason for Non-Accreditation
E12: Start Date (MMM-DD-YYYY) | F12: End Date (MMM-DD-YYYY)
A13: Main Campus, Quezon City, Manila
A14: 1 | B14: Bachelor in Secondary Education Major in English | C14: 2012 | D14: Candidate | G14: Preliminary Survey conducted last November 20-23, 2023. Scanned copy of the report can be accessed here: tinyurl.com/SampleLink
A15: 2 | B15: Bachelor in Secondary Education Major in Mathematics | C15: 2003 | D15: Level 1 | E15: 43312 | F15: 44043 | G15: Accreditation certificate lapsed due to deficiency of requirements; scheduled for accreditation visit on February 12, 2024. Communication with AACCUP regarding the schedule is attached. Scanned copy of this file can be accessed here: tinyurl.com/SampleLink
A16: 3 | B16: Bachelor in Secondary Education Major in Science | C16: 2000 | D16: Level 2 | E16: 44926 | F16: 45657 | G16: AACCUP Accreditation Certificate
A17: 4 | B17: Bachelor of Arts in Social Sciences | C17: 1999 | D17: Level 3 | E17: 44926 | F17: 45657 | G17: AACCUP Accreditation Certificate
A18: 5 | B18: Bachelor of Science in Accountancy | C18: 1984 | D18: Level 4 | E18: 44927 | F18: 46752 | G18: AACCUP Accreditation Certificate
A19: 6 | B19: Bachelor of Science in Civil Engineering | C19: 2022 | D19: Not Accreditable | G19: Program is being offered for less than five (5) years and has not yet reached the required batch of graduates.
A21: 1 | C21: 2 | D21: 3 | E21: 4 | G21: 5
A22: Undergraduate Programs Offered | C22: Year of Initial Operation | D22: Program Accreditation Status | E22: Validity of Accreditation (Ref. Accreditation Certificate) | G22: Supporting Documentation
E23: Start Date (MMM-DD-YYYY) | F23: End Date (MMM-DD-YYYY)
A24: MSC Boac Main Campus (Tanza, Boac, Marinduque)
A25: 1 | B25: Bachelor of Secondary Education | C25: 1986-1987 | D25: Level III Re- Accredited | E25: October 1, 2022 | F25: 45170 | G25: BSED.pdf
A26: 2 | B26: BS in Civil Engineering | C26: 1998-1999 | D26: Level III Re- Accredited | E26: May 16, 2021 | F26: May 15, 2025 | G26: https://drive.google.com/file/d/1RBZJ4kbt7M8Uw36U8kBNqZioFKRZFaTW/view?usp=drive_link
A27: 3 | B27: BS in Electrical Engineering | C27: 1998-1999 | D27: Level III Re- Accredited | E27: May 16, 2021 | F27: May 15, 2025 | G27: https://drive.google.com/file/d/1I7pFuxdlxG3_9VejHJooifR9q174QeKB/view?usp=drive_link
A28: 4 | B28: BS in Computer Engineering | C28: 2008-2009 | D28: Level III Re- Accredited | E28: July 1, 2021 | F28: June 30, 2025 | G28: https://drive.google.com/file/d/1E2AoSD-jmdxJHuHAh1SOU7QVAde-1U5x/view?usp=drive_link
A29: 5 | B29: BS in Electronics Engineering | C29: 2008-2009 | D29: Level III Re- Accredited | E29: July 1, 2021 | F29: June 30, 2025 | G29: https://drive.google.com/file/d/1gPyRbIskD43gzfdEnNAKOTNsW56-9wRu/view?usp=sharing
A30: 6 | B30: BS in Information Systems | C30: 1998-1999 | D30: Level III Re- Accredited | E30: January 1, 2020 | F30: December 31, 2023 | G30: https://drive.google.com/file/d/1TjtAhJbaW98X-MEjpgqDIjyhjE-78xtQ/view?usp=drive_link
A31: 7 | B31: BS in Information Technology | C31: 1998-1999 | D31: Level III Re- Accredited | E31: January 1, 2020 | F31: December 31, 2023 | G31: https://drive.google.com/file/d/1BLZlFIoQdzvY57nA3F49Od6rovaLsN06/view?usp=drive_link
A32: 8 | B32: BS in Industrial Technology maj in Automotive, Mechanical, Food, Electrical, Drafting, Refrigiration & Air conditioning & Welding and fabrication | C32: 1989-1990 | D32: Level III Re- Accredited | E32: January 1, 2020 | F32: December 31, 2023 | G32: https://drive.google.com/file/d/1AzxNReDjg1wh4i_8amlC-nwN_iC8_mZT/view?usp=sharing
A33: 9 | B33: BA in Communication | C33: 2010-2011 | D33: Level III Re- Accredited | E33: October 16, 2021 | F33: October 15, 2025 | G33: https://drive.google.com/file/d/1KPFKZLaR3rj5BdHV0gPxyYZWTyWS9i3k/view?usp=sharing
A34: 10 | B34: BA in English Language Studies | C34: 2006-2007 | D34: Level III Re- Accredited | E34: October 16, 2021 | F34: October 15, 2025 | G34: https://drive.google.com/file/d/1gBf2ddZ5SrF2zCfKzNz2tFrkgLSzSWO_/view?usp=sharing
A35: 11 | B35: BS in Entrepreneurship | C35: 2006-2007 | D35: Level III Re- Accredited | E35: July 1, 2021 | F35: June 30, 2025 | G35: https://drive.google.com/file/d/1ftqttYhNaFBFXdPCPrzIQTBZ3nynLzJC/view?usp=sharing
A36: 12 | B36: BS in Nursing | C36: 2006-2007 | D36: Level III Re- Accredited | E36: July 1, 2021 | F36: June 30, 2025 | G36: https://drive.google.com/file/d/1vYaVHLoxzRtf-6Zs3A4Qp1_02C-R7BEM/view?usp=sharing
A37: 13 | B37: Bachelor of Public Administration | C37: 2012-2013 | D37: Level II Re- Accredited | E37: July 1, 2022 | F37: June 30, 2026 | G37: https://drive.google.com/file/d/12luzk4O4EYlQGQppOay4M1JzdRBRpOjS/view?usp=sharing
... A46: 22 | B46: BS in Business Administration | C46: 2018-2019 | D46: Accreditable | E46: N/A | F46: N/A | G46: (For Preliminary Survey Visit)
A47: MSC Sta.Cruz Campus
A48: 1 | B48: Bachelor of Elementary Education major in Pre-Elementary & General Education | C48: 1992-1993 | D48: Level 3 | E48: December 16, 2020 | F48: December 15, 2024 | G48: https://drive.google.com/file/d/12nYQlPZZKFKkDkiXavMzmHAaXRjvTSz5/view?usp=sharing
A49: 2 | B49: AB in Political Science | C49: 1992-1993 | D49: Level 2 | E49: October 1, 2022 | F49: 45170
A50: 3 | B50: BS in Information Systems (SC) | C50: 1998-1999 | D50: Level 2 | E50: 44378 | F50: 46174
A51: 4 | B51: BS in Tourism Management | C51: 2007-2008 | D51: Level 3 | E51: July 1, 2021 | F51: June 30, 2025 | G51: https://drive.google.com/file/d/1v-lIyglsXtneDx1F3CU4e3Ewrj54in2u/view?usp=sharing
A52: MSC Torrijos Campus
A53: 1 | B53: BS in Agricultural Technology | C53: 2012-2013 | D53: Level 2 | E53: N/A | F53: N/A | G53: (For gradual Phase out as per BOT No.41,s.2023)
A54: 2 | B54: BS Entrep major in Agri business | C54: 2012-2013 | D54: Level 2 | E54: November 1, 2018 | F54: October 31, 2022 | G54: https://drive.google.com/file/d/1aXRLHJN3elPSQkmOiXPkUbFl-oY-WhtB/view?usp=sharing
A55: 3 | B55: BS in Agriculture | C55: 2006-2007 | D55: Level 2 | E55: July 1, 2022 | F55: June 30, 2026 | G55: https://drive.google.com/file/d/1AiV4R8TLzOf5zsgaMveI6edBgYHjm1Tg/view?usp=sharing
A56: MSC Gasan Campus
A57: 1 | B57: BS in Fisheries | C57: 1985-1986 | D57: Level 3 | E57: July 1, 2021 | F57: June 30, 2025 | G57: https://drive.google.com/file/d/1HUXVYh8nEoGoY3mkzF3uRxobfLRqVS6r/view?usp=sharing
B59: Number of Programs Offered: | D59: =COUNTIFS($B25:B58,"<>",D25:D58,"<>") -> 30
B60: Number of Accredited Programs: | D60: 23
B61: Number of Accreditable Programs: | D61: 30
B62: PERCENTAGE | D62: =D60/D61 -> 0.76666667
A64: Prepared by:
B67: MENANDRO M. MERLIN, DEM | C67: 45348
B68: IQA Director | C68: Date
A71: Approved:
B74: Prof. DIOSDADO P. ZULUETA, DPA | C74: 45348
B75: SUC President III | C75: Date

Sheet Advanced Education (Oc1)
B1: NAME OF INSTITUTION: | C1: (MARINDUQUE STATE COLLEGE)
B2: PROGRAM: | C2: ADVANCED EDUCATION PROGRAM
B3: INDICATOR/S: | C3: Outcome Indicator 1: Percentage of graduate school faculty engaged in research work applied in any of the following: a) pursuing advanced research degree programs (doctorate degree) or b) actively pursuing within the last three (3) years (investigative research, basic and applied scientific research, policy research, social science research) or c) producing technologies for commercialization or livelihood improvement or d) whose research work resulted in an extension program
B4: INSTRUCTIONS: | C4: Kindly fill out Column 1 by listing all graduate school faculty members. In Column 2, list the position or designation of the respective faculty members. In Column 3, select the category of engagement of each listed faculty member. In Column 4, list down the documents submitted to verify the information provided in the previous columns. You may provide links to the electronic copies of supporting documents in this column.
B5: REFERENCES: | C5: ='[1]Reference Matrix'!$E11 -> 0
B6: MEANS OF VERIFICATION: | C6: ='[1]Reference Matrix'!$F11 -> 0
B7: LINK TO GOOGLE DRIVE FOLDER: | C7: (https://drive.google.com/drive/folders/1Zezs1rJYwXox2umra5r2TT9W34aBuL09?usp=drive_link)
A9: SAMPLE
A10: 1 | C10: 2 | D10: 3 | E10: 4
A11: Name of Faculty | C11: Position | D11: Category | E11: Supporting Documentation / Means of Verification
A12: 1 | B12: Surname, First Name, MI. | C12: Instructor I | D12: A: Pursuinng advance degree programs | E12: Scanned copy of enrollment form
A13: 2 | B13: Cruz, Juana E. | C13: Associate Professor II | D13: B: Actively pursing research within the last three (3) years | E13: Scanned copy of latest research conducted
A14: 3 | B14: Dela Cruz, Juan M. | C14: Associate Professor III | D14: C: Producing technologies for commercialization or livelihood improvement | E14: Documentation of utilized technlogy
A15: 4 | B15: Flores, John D. | C15: University Professor V | D15: D: Whose research work resulted in an extension program | E15: Activity report of extension program
A16: 5 | B16: Reyes, Jose G. | C16: Board Secretary | D16: E: Not applicable
A17: 6 | B17: Santos, Joanna L. | C17: Associate Professor I | D17: A: Pursuinng advance degree programs | E17: Scanned copy of enrollment form
A19: 1 | C19: 2 | D19: 3 | E19: 4
A20: Name of Faculty | C20: Position | D20: Faculty Engagement | E20: Supporting Documentation / Means of Verification
A21: {=IFERROR(SEQUENCE(COUNTA(B21:B40)),1)} -> 1 | B21: Atienza, Cristina S. | C21: I1 | D21: E: Not applicable
A22: 2 | B22: Benedicto, Wilbert P. | C22: I1 | D22: E: Not applicable
A23: 3 | B23: Blase, Ma. Edelwina M. | C23: P4 | D23: B: Actively pursing research within the last three (3) years | E23: Documentation
A24: 4 | B24: Capina, Verna Liza L. | C24: ASO5 | D24: E: Not applicable
A25: 5 | B25: Cuevas, Abraham L. | C25: ASO2 | D25: E: Not applicable
A26: 6 | B26: Go, Vili Dane M. | C26: I1 | D26: E: Not applicable
A27: 7 | B27: Jalos, Leodegario Jr. M. | C27: ASO5 | D27: E: Not applicable
A28: 8 | B28: Labatete, Anne Grace M. | C28: ASO2 | D28: B: Actively pursing research within the last three (3) years | E28: Documentation
A29: 9 | B29: Malvar, Romulo H. | C29: CP | D29: E: Not applicable
A30: 10 | B30: Manoos, Liza Marie M. | C30: ASO5 | D30: E: Not applicable
A31: 11 | B31: Montejo, Joy S. | C31: ASOI | D31: E: Not applicable
A32: 12 | B32: Nabos, Christine May L. | C32: I1 | D32: B: Actively pursing research within the last three (3) years | E32: Documentation
A33: 13 | B33: Nabos, Julieta Q. | C33: ASO2 | D33: C: Producing technologies for commercialization or livelihood improvement | E33: Documentation
A34: 14 | B34: Palomares, Noel R. | C34: ASI3 | D34: D: Whose research work resulted in an extension program | E34: Documentation
A35: 15 | B35: Pineda, Susan B. | C35: ASO5 | D35: B: Actively pursing research within the last three (3) years | E35: Documentation
A36: 16 | B36: Regalia, Marites R. | C36: I1 | D36: E: Not applicable
A37: 17 | B37: Ricafrente, Jellian T. | C37: ASO2 | D37: E: Not applicable
A38: 18 | B38: Zulueta, Diosdado P. | C38: CP | D38: E: Not applicable
D41: PERCENTAGE
B42: A: | C42: =COUNTIF($D$21:$D$40, "*"&B42&"*") -> 0 | D42: =$C42/$C$47 -> 0
B43: B: | C43: =COUNTIF($D$21:$D$40, "*"&B43&"*") -> 4 | D43: =$C43/$C$47 -> 0.22222222
B44: C: | C44: =COUNTIF($D$21:$D$40, "*"&B44&"*") -> 1 | D44: =$C44/$C$47 -> 0.055555556
B45: D: | C45: =COUNTIF($D$21:$D$40, "*"&B45&"*") -> 1 | D45: =$C45/$C$47 -> 0.055555556
B46: E: | C46: =COUNTIF($D$21:$D$40, "*"&B46&"*") -> 12
B47: TOTAL: | C47: =SUM(C42:C46) -> 18 | D47: =SUM(D42:D46) -> 0.33333333
A49: Prepared by:
B52: JULIETA Q. NABOS, PhD | C52: 45348
B53: Dean, Graduate School | C53: Date
A56: Approved:
B59: Prof. DIOSDADO P. ZULUETA, DPA | C59: 45348
B60: SUC President III | C60: Date

Sheet Advanced Education (Op1_SC)
B1: NAME OF INSTITUTION: | C1: (MARINDUQUE STATE COLLEGE)
B2: PROGRAM: | C2: ADVANCED EDUCATION PROGRAM
B3: INDICATOR/S: | C3: Output Indicator 1 For State Colleges and Professional Institutes: Percentage of graduate students enrolled in CHED-identified or RDC-identified priority programs
B4: INSTRUCTIONS: | C4: Kindly fill out Column 1 by listing all graduate programs offered in each campus. Please do not abbreviate or shorten program names. In Column 2, identify if the program offered is a priority program using the references listed below. In Column 3, input the number of enrollees for each corresponding program. In Column 4, list down the documents submitted to verify the information provided in the previous columns. You may provide links to the electronic copies of supporting documents in this column.
B5: REFERENCES: | C5: {="For State Colleges and Professional Institutes:"&CHAR(10)&'Reference Matrix'!$E13} -> For State Colleges and Professional Institutes: References in determining the disciplines/programs identified as priority offerings: a. CMO No. 5, s. 2019 b. CMO No. 10, s. 2021 c. CMO No. 7, s. 2023 d. RDC Resolutions
B6: MEANS OF VERIFICATION: | C6: {="For State Colleges and Professional Institutes:"&CHAR(10)&'Reference Matrix'!$F13} -> For State Colleges and Professional Institutes: 1. Duly certified enrollment report 2. Summary of Enrolment by identified priority graduate programs, and all other programs per campus 3. For programs considered priority outside those identified by the CHED, submit certification, resolution from RDC or similar Government Councils, etc.
B7: LINK TO GOOGLE DRIVE FOLDER: | C7: (https://drive.google.com/drive/folders/1Zezs1rJYwXox2umra5r2TT9W34aBuL09?usp=drive_link)
A9: SAMPLE
A10: 1 | C10: 2 | E10: 3
A11: Undergraduate Program Offered | C11: No. of Enrollees for 1st Semester AY 2023-2024 | E11: Supporting Documentation
C12: Priority Program | D12: Non-Priority Program
A13: Main Campus, Quezon City, Manila | E13: 1. Certified Report for Graduate Students Enrolled in 1st Semester AY 2023-2024 2. CHED Memorandum Order No. 10, s. 2021 3. RDC Resolutions
A14: 1 | B14: Doctor of Philosophy in Agriculture | C14: 88
A15: 2 | B15: Doctor of Philosophy in Education | C15: 78
A16: 3 | B16: Doctor of Public Administration | D16: 112
A17: 4 | B17: Master in Information Technology | C17: 10
A18: 5 | B18: Master in Public Administration | D18: 89
A19: 6 | B19: Master in Business Administration | C19: 90
A21: 1 | C21: 2 | E21: 3
A22: Undergraduate Program Offered | C22: No. of Enrollees for 1st Semester AY 2023-2024 | E22: Supporting Documentation
C23: Priority Program | D23: Non-Priority Program
A24: Main Campus (Please identify the name of campus and location)
A25: 1 | B25: Doctor of Education | C25: 43
A26: 2 | B26: Master Arts in Education | C26: 457
A27: 3 | B27: Master of Public Administration | C27: 45 | D27: 30
A28: 4 | B28: Master in Information Technology | C28: 7
A29: 5
B31: Sub Total | C31: =SUM(C25:C30) -> 552 | D31: =SUM(D25:D30) -> 30
B32: Total Number of Enrollees | C32: =SUM(C31:D31) -> 582
B33: PERCENTAGE | C33: =C31/C32 -> 0.94845361
A35: Prepared by:
B38: GEMMA A. TIROL | C38: 45348
B39: College Registrar | C39: Date
A42: Approved:
B45: Prof. DIOSDADO P. ZULUETA, DPA | C45: 45348
B46: SUC President III | C46: Date

Sheet Advanced Education (Op2)
B1: NAME OF INSTITUTION: | C1: (MARINDUQUE STATE COLLEGE)
B2: PROGRAM: | C2: ADVANCED EDUCATION PROGRAM
B3: INDICATOR/S: | C3: Output Indicator 2: Percentage of accredited graduate programs
B4: INSTRUCTIONS: | C4: In Column 1, list down all graduate degree programs offered by the institution. Input the Year of Initial Operation of each degree program in Column 2. In Column 3, select the Program Accreditation Status of each program from the dropdown menu. In Column 4, provide the Validity of Accreditation of each program. Refer to the issued accreditation certificate. Provide descriptions and links to supporting documentation in Column 5.
B5: REFERENCES: | C5: ='Reference Matrix'!$E14 -> Accreditation includes those issued by local and international bodies recognized by CHED; AACCUP (Level 1 - Level 4)
B6: MEANS OF VERIFICATION: | C6: ='Reference Matrix'!$F14 -> 1. Accreditation Certificates 2. List of all graduate programs per campus with or without accreditation (include reasons for non-accreditation), indicate year of initial operation
B7: LINK TO GOOGLE DRIVE FOLDER: | C7: (https://drive.google.com/drive/folders/1Zezs1rJYwXox2umra5r2TT9W34aBuL09?usp=drive_link)
A9: SAMPLE
A10: 1 | C10: 2 | D10: 3 | E10: 4 | G10: 5
A11: Undergraduate Programs Offered | C11: Year of Initial Operation | D11: Program Accreditation Status | E11: Validity of Accreditation (Ref. Accreditation Certificate) | G11: Supporting Documentation / Reason for Non-Accreditation
E12: Start Date (MMM-DD-YYYY) | F12: End Date (MMM-DD-YYYY)
A13: Main Campus, Quezon City, Manila
A14: 1 | B14: Master in Information Technology | C14: 2012 | D14: Candidate | G14: Preliminary Survey conducted last November 20-23, 2023. Scanned copy of the report can be accessed here: tinyurl.com/SampleLink
A15: 2 | B15: Master in Public Administration | C15: 2003 | D15: Level 1 | E15: 43312 | F15: 44043 | G15: Accreditation certificate lapsed due to deficiency of requirements; scheduled for accreditation visit on February 12, 2024. Communication with AACCUP regarding the schedule is attached. Scanned copy of this file can be accessed here: tinyurl.com/SampleLink
A16: 3 | B16: Master in Business Administration | C16: 2000 | D16: Level 2 | E16: 44926 | F16: 45657 | G16: AACCUP Accreditation Certificate
A17: 4 | B17: Doctor of Philosophy in Agriculture | C17: 1999 | D17: Level 3 | E17: 44926 | F17: 45657 | G17: AACCUP Accreditation Certificate
A18: 5 | B18: Doctor of Philosophy in Education | C18: 1984 | D18: Level 4 | E18: 44927 | F18: 46752 | G18: AACCUP Accreditation Certificate
A19: 6 | B19: Doctor of Public Administration | C19: 2022 | D19: Not Accreditable | G19: Program is being offered for less than five (5) years and has not yet reached the required batch of graduates.
A21: 1 | C21: 2 | D21: 3 | E21: 4 | G21: 5
A22: Undergraduate Programs Offered | C22: Year of Initial Operation | D22: Program Accreditation Status | E22: Validity of Accreditation (Ref. Accreditation Certificate) | G22: Supporting Documentation
E23: Start Date (MMM-DD-YYYY) | F23: End Date (MMM-DD-YYYY)
A24: MSC Boac Main Campus (Tanza, Boac, Marinduque)
A25: 1 | B25: Master of Arts in Education major in Educational Management | C25: 1987-1988 | D25: Level 3 | E25: October 1, 2023 | F25: 46660 | G25: https://drive.google.com/file/d/1xsdZO-ctsqogSlVqtNkjDeEDdg3U1uYI/view?usp=sharing
A26: 2 | B26: Master in Public Administration major in: Organizational Studies/ Local Government and Regional Administration | C26: 1995-1996 | D26: Level 3 | E26: October 1, 2023 | F26: 46660 | G26: https://drive.google.com/file/d/1xsdZO-ctsqogSlVqtNkjDeEDdg3U1uYI/view?usp=sharing
A27: 3 | B27: Doctor of Education major in Curriculum Development and Management | C27: 2008-2009 | D27: Level 2 | E27: October 1, 2022 | F27: 45170 | G27: https://drive.google.com/file/d/1-OJ0wAAgggVvXPwl9uBq4C0cgqvEVOXJ/view?usp=sharing
B29: Number of Programs Offered: | D29: =COUNTIFS($B25:B28,"<>",D25:D28,"<>") -> 3
B30: Number of Accredited Programs: | D30: 3
B31: Number of Accreditable Programs: | D31: =D29-COUNTIF(D25:D28,"Not Accreditable") -> 3
B32: PERCENTAGE | D32: =D30/D31 -> 1
A35: Prepared by:
B38: MENANDRO M. MERLIN, DEM | C38: 45348
B39: IQA Director | C39: Date
A42: Approved:
B45: Prof. DIOSDADO P. ZULUETA, DPA | C45: 45348
B46: SUC President III | C46: Date

Sheet Research Program (Op&Oc)
B1: NAME OF INSTITUTION: | C1: (MARINDUQUE STATE COLLEGE)
B2: PROGRAM: | C2: RESEARCH PROGRAM
B3: INDICATOR/S: | C3: Outcome Indicator 1: Number of research outputs in the last three years (FY 2021-2023) utilized by the industry or by other beneficiaries Output Indicator 1: Number of research outputs completed within the year Output Indicator 2 (For State Universities): Percentage of researches published within the year (FY 2023) in internationally-refereed journal Output Indicator 2 (For State Colleges and Professional Institutes): Percentage of researches presented within the year (FY 2023) in national, regional, and international fora
B4: INSTRUCTIONS: | C4: In the columns under Details of Research Outputs, list all faculty research outputs completed within the past three years. Please include the year of completion for each research output listed. For each research output, fill in the corresponding information on its presentation, publication, and/or utilization. Kindly fill all fields. Please indicate N/A if the field is not applicable for the research output. For State Colleges, please fill in the requested information under the Details of Presentation columns of corresponding research outputs completed in FY 2021, 2022, and 2023. Please note that in-house presentations/reviews will not be considered. For State Universities, please fill in the requested information under Details of Publication columns of corresponding research outputs completed in FY 2021, 2022, and 2023. Please be reminded that incomplete entries in this form will be disregarded.
B5: REFERENCES: | C5: {="For Outcome Indicator 1:"&CHAR(10)&'Reference Matrix'!$E16&CHAR(10)&CHAR(10)&"For Output Indicator 1:"&CHAR(10)&'Reference Matrix'!$E17&CHAR(10)&CHAR(10)&"For Outcome Indicator 2 (State Universities):"&CHAR(10)&'Reference Matrix'!$E18&CHAR(10)&CHAR(10)&"For Outcome Indicator 2 (State Colleges and Professional Institutes):"&CHAR(10)&'Reference Matrix'!$E19} -> For Outcome Indicator 1: Utilized by industry or other beneficiaries refers to the adopters/partners/communities, external to the institution For Output Indicator 1: Research outputs may comprise any or all of the following: 1. Completed research-based papers; 2. Research-based papers or articles published in journals or international refereed publications that are not in the Beall's List of Predatory Journals; 3. Research-based papers or articles presented in international, national, or regional fora or conferences; 4. Inventions or innovations, methods, composition, or processes as a result of research 5. Models/inventions duly patented and applied for commercial purposes or utilized/adopted for development/production/service provision For Outcome Indicator 2 (State Universities): Beall's List of Predatory Journals Documentation on the details of journals to qualify in internationally refereed journals For Outcome Indicator 2 (State Colleges and Professional Institutes): In-house review presentations are not included nor considered as presentations in qualified fora.
B6: MEANS OF VERIFICATION: | C6: ="For Outcome Indicator 1:"&CHAR(10)&'Reference Matrix'!$F16&CHAR(10)&CHAR(10)&"For Output Indicator 1:"&CHAR(10)&'Reference Matrix'!$F17&CHAR(10)&CHAR(10)&"For Outcome Indicator 2 (State Universities):"&CHAR(10)&'Reference Matrix'!$F18&CHAR(10)&CHAR(10)&"For Outcome Indicator 2 (State Colleges and Professional Institutes):"&CHAR(10)&'Reference Matrix'!$F19 -> For Outcome Indicator 1: 1. Proof that the research output was utilized by identified stakeholders/beneficiaries 2. MOAs/MOUs 3. Reports with testimonies 4. Certification from industries/beneficiaries on the utilization of research outputs For Output Indicator 1: 1. Abstracts of research outputs 2. Certificate of completion signed by the Research Director/Vice President for Research For Outcome Indicator 2 (State Universities): 1. Photocopy of the journal's title page, and 1st page of the article published For Outcome Indicator 2 (State Colleges and Professional Institutes): 1. Conference proceeding indicating research article presented 2. Program of activities and attendance to the conference 3. Certificate of participation / recognition for presenting the research output
B7: LINK TO GOOGLE DRIVE FOLDER: | C7: (https://drive.google.com/drive/folders/1Zezs1rJYwXox2umra5r2TT9W34aBuL09?usp=drive_link)
A9: SAMPLE
A10: Details of Research Outputs | G10: Details of Presentation | K10: Details of Publication | Q10: Details of Utilized Output
A11: Research Title | C11: Name of Faculty Researcher / Author | D11: Status of Research | E11: Duration of Research | G11: Title of Forum | H11: Venue | I11: Forum Type | J11: Date of Presentation (MMM-DD-YYYY) | K11: Published Title | L11: Date of Publication (MMM-DD-YYYY) | M11: Title of Journal / Publication | N11: Volume & Issue | O11: ISSN / ISBN | P11: Index | Q11: Product Name / Methods / Process / Technology | R11: Patent Number / Product Description | S11: Benefiting Industry / Community
E12: Date Started (MMM-DD-YYYY) | F12: Date of Completion (MMM-DD-YYYY)
A13: 1 | B13: Sample Research Title 1 | C13: Flores, John D. | D13: Completed | E13: 43479 | F13: 45138 | G13: N/A | H13: N/A | I13: N/A | J13: N/A | K13: Sample Research Title 1 | L13: 45212 | M13: Journal of Environmental Science and Management | N13: Volume 26 No 1 (2023) | O13: SSN 0119-1144 | P13: Science Citation Index Expanded | Q13: Product of Sample Research 1 | R13: This product represents the culmination of rigorous research, offering a comprehensive and cutting-edge approach to develop new products from recyclable materials which can be commercialized for profit of small and medium enterprises. | S13: Small and medium-sized enterprises (SMEs)
A14: 2 | B14: Sample Research Title 2 | C14: Santos, Joanna L. | D14: Completed | E14: 44480 | F14: 44855 | G14: Knowledge Nexus: Exploring Frontiers in Research | H14: Philippine International Convention Center, PICC Complex, Pasay, Manila | I14: National | J14: 44887 | K14: Sample Research Title 2 | L14: 44908 | M14: Journal of Environmental Science and Management | N14: Volume 26 No 1 (2023) | O14: SSN 0119-1144 | P14: Science Citation Index Expanded | Q14: N/A | R14: N/A | S14: N/A
A15: 3 | B15: Sample Research Title 3 | C15: Dela Cruz, Juan M. | D15: Completed | E15: 43843 | F15: 44571 | G15: Regional Insight Summit: Unveiling Perspectives through Local Research Excellence | H15: SMX Convention Center, Clark, Pampanga | I15: Regional | J15: 45037 | K15: N/A | L15: N/A | M15: N/A | N15: N/A | O15: N/A | P15: N/A | Q15: N/A | R15: N/A | S15: N/A
A16: 4 | B16: Sample Research Title 4 | C16: Cruz, Juana E. | D16: Completed | E16: 43549 | F16: 44200 | G16: Global Symposium on Advanced Research and Innovation 2023 | H16: Renaissance Convention Center, Singapore | I16: International | J16: 44279 | K16: N/A | L16: N/A | M16: N/A | N16: N/A | O16: N/A | P16: N/A | Q16: N/A | R16: N/A | S16: N/A
A17: 5 | B17: Sample Research Title 5 | C17: Cruz, Juana E. | D17: On-going | E17: 45243
A19: Details of Research Outputs | G19: Details of Presentation | K19: Details of Publication | Q19: Details of Utilized Output
A20: Research Title | C20: Name of Faculty Researcher / Author | D20: Status of Research | E20: Duration of Research | G20: Title of Forum | H20: Venue | I20: Forum Type | J20: Date of Presentation | K20: Published Title | L20: Date of Publication | M20: Title of Journal / Publication | N20: Volume & Issue | O20: ISSN / ISBN | P20: Index | Q20: Product Name / Methods / Process / Technology | R20: Patent Number / Product Description | S20: Benefiting Industry / Community
E21: Date Started (MMM-DD-YYYY) | F21: Date of Completion (MMM-DD-YYYY)
B22: 2023
A23: 1 | B23: Level of Satisfaction of the Residents of Brgy. Pili, Mogpog, Marinduque on Government Service Delivery | C23: Generoso E. Udanga Abraham L. Cuevas | D23: Completed | E23: 44850 | F23: 44941 | G23: PSU BIMP-EAGA International Research Conference | H23: City State Asturias Hotel, Puerto Princesa, Palawan | I23: International | J23: 44966 | Q23: E-salba for Disaster and Health Risk Reduction | R23: This activity is a result of the research collaboration with Mapua University about the development of health index: vulnerability to extreme environmental events for Marinduque Island with the e-Salba user application to be used for health and disaster risk reduction in the province of Marinduque. | S23: Local Government Units of Marinduque
A24: 2 | B24: Lived Experiences of Selected MSMEs on Technological Assistance | C24: Michael V. Capiña | D24: Completed | E24: 44829 | F24: 44951 | G24: 2023 International Conference on Sustainable Agri-vironment Education, Entrepreneurship, and Community Development (ICSAVED) | H24: Mariano Marcos State Univeristy | I24: International | J24: March 14-17, 2023
A25: 3 | B25: Tracer Study of Diploma in Midwifery Graduates in the Marinduque State College from 2006-2022 | C25: Abegail O. Magcamit | D25: Completed | E25: 44835 | F25: 44986 | G25: 35th APSOM Annual Convention – Association of Philippine Schools of Midwifery, Inc | H25: Century Park Hotel, Malate, Manila | I25: National | J25: April 19-20, 2023
A26: 4 | B26: Level of Satisfaction in Maternal and Child Health Care Services of the BEmONC Facility as perceived by parents in Ten Barangays of Buenavista, Marinduque, Philippines | C26: Divina R. Vitto | D26: Completed | E26: 44621 | F26: 44987 | G26: 35th APSOM Annual Convention – Association of Philippine Schools of Midwifery, Inc | H26: Century Park Hotel, Malate, Manila | I26: National | J26: April 19-20, 2023
A27: 5 | B27: Training Needs Assessment of Barangay Officials in the Municipalities of Torrijos and Buenavista, Marinduque | C27: Joy R. Profugo Wilmer L. Imperio Neil Ryan P. Rodil | D27: Completed | E27: 44866 | F27: 45017 | G27: 6th International Conference in Research, Education, Management, and the Social Sciences | H27: Crown Legacy Hotel, Baguio City | I27: International | J27: April 15-17, 2023 | Q27: Rapid Assessment of Cave | R27: This is a product of the research on : Cave Bio-physical Characterization: GIS - Based Mapping in partnership with DENR-PENRO for the assessment and mapping of uncharted caves in the province of Marinduque | S27: DENR-PENRO
A28: 6 | B28: Evaluating Resident Satisfaction with Tourism Promotion Program in Barangay Pili, Mogpog, Marinduque: Implications to Local Tourism Management | C28: Generoso E. Udanga | D28: Completed | E28: 44850 | F28: 44941 | G28: International Hospitality and Tourism Research AMPAYAG: 1st International Conference Conference | H28: Laoag City, Ilocos Norte | I28: International | J28: May 18-19, 2023 | Q28: Effective management of Marinduque Wildlife Sanctuary | R28: This initiative is part of the ongoing partnership with DENR-PENRO on the Biophysical, Socio-Economic and Vulnerability Assessments of the Marinduque Wildlife Sanctuary (MWS): A Basis for the Formulation of the Protected Area Management Plan for a resilient and effective management of MWS in Tumagabok, Marinduque | S28: LGU Boac PAMB, PAMO, TSD Staff
A29: 7 | B29: Kaligtasan 2050: Emerging Trends and Futures in Marinduque Safety and Security Scenario | C29: Katrina E. De Mesa Portia RZ. Hermosa | D29: Completed | E29: 11/20/2023 | F29: 4/20/2023 | G29: DLSU D National Conference on Technology and Research for National Development and Sustainability (TReNDS) | H29: DLSU Dasmarinas | I29: National | J29: May 24-26, 2023
A30: 8 | B30: CFD-Based Surface Runoff Simulation Model as a Tool for a Flood Control System | C30: Rester JiNang | D30: Completed | E30: 11-15-2022 | F30: 4-15-2023 | G30: 2nd International Conference on Climate Change Adaptation (CCA) and Disaster Risk Reduction Management (DRRM) | H30: Amari Don Muang Airport Hotel, Bangkok, Thailand. | I30: International | J30: May 29-June 2, 2023 | Q30: Capacity Building of Protected Area Management | R30: This initiative is part of the ongoing partnership with DENR-PENRO on the Biophysical, Socio-Economic and Vulnerability Assessments of the Marinduque Wildlife Sanctuary (MWS): A Basis for the Formulation of the Protected Area Management Plan for a resilient and effective management of MWS in Tumagabok, Marinduque | S30: Marinduque Wildlife Sanctuary PAMB, TSD, PAMO
A31: 9 | B31: Interpreting the Marinduque Provincial Government and Fisherfolks’ relation on development projects: Towards a policy of co-governance in public administration | C31: Hilaron R. Elegado | D31: Completed | E31: 1/15/2023 | F31: 44931 | G31: 2023 Political Science Association International Conference | H31: Western Visayas State University | I31: International | J31: June 7-8, 2023
A32: 10 | B32: The Perceived Impact of Legislative Actions taken by the Sangguniang Bayan of Sta. Cruz, Marinduque | C32: Anne Grace M. Labatete Wilmer L. Imperio | D32: Completed | E32: 2/20/2023 | F32: 5/20/2023 | G32: 2023 Political Science Association International Conference | H32: Western Visayas State University | I32: International | J32: June 7-8, 2023 | Q32: Capacitating Educators in Research and Challenge Areas | R32: This is a result of the Training Needs Assessment for DepEd Schools: Basis for an Extension Project of the Marinduque State College-School of Education in partnership with the Deped of Education Marinduque to capacitate the DepEd teachers in various areas of discipline. | S32: Deped Marinduque
A33: 11 | B33: Wildlife Awareness Educational Simulation Game | C33: Doreena Joy C. Borja Darrel J. Nambio Elgemar M. Natal Jhon Rynel S. Tan | D33: Completed | E33: 45047 | F33: 05/31/2023 | G33: 2nd International Computing and Information Sciences Conference | H33: Caraga State University, Butuan City | I33: International | J33: June 8-9, 2023
A34: 12 | B34: Towards Achieving the Sustainable Development Goals: Identifying Economic and Investment Priorities in Barangay Pili, Mogpog | C34: Generoso E. Udanga | D34: Completed | E34: 12/15/2022 | F34: 4/15/2023 | G34: 6th International Multidisciplinary Research Conference | H34: Leyte Normal University, Tacloban City, Leyte | I34: International | J34: June 27-29, 2023
A35: 13 | B35: Revisiting the Socio-economic and health impacts of the Marcopper Mine Disaster, 20 years after | C35: Evangeline B. Mandia | D35: Completed | E35: 44567 | F35: 44932 | G35: 3rd International Conference on Indigenous Knowledge System and Practices (IKSP) amidst Growing Ecological Challenges: Transdisciplinary Perspectives from Global South | H35: Yogyakarta Universitas Ahmad, Dahlan, Indonesia | I35: International | J35: July 5-7, 2023
A36: 14 | B36: Socio-Economic, Political Orientations, and Literacy Development of People in Salomague Island in Marinduque, Philippines: A Phenomenological Study | C36: Hilarion R. Elegado Annalyn J. Decena Kevin Marasigan | D36: Completed | E36: 5/15/2022 | F36: 5/15/2023 | G36: International Conference on Academic Research and Innovation (ICARI 2023) | H36: Thu Duc College of Technology, Ho Chi Minh, Vietnam – via Zoom | I36: International | J36: July 6-8, 2023
A37: 15 | B37: The Perceived Impact Of 1-3-5 Rating Technique To The Language Proficiency And Confidence Of The Graduates Of Bachelor Of Elementary Education (Beed) | C37: Annalyn J. Decena | D37: Completed | E37: 45047 | F37: 45051 | G37: International Conference on Academic Research and Innovation (ICARI 2023) | H37: Thu Duc College of Technology, Ho Chi Minh, Vietnam | I37: International | J37: July 6-8, 2023
A38: 16 | B38: Ex-post aquatic Impact Assessment of Mined-out areas in Boac, Marinduque, Philippines: Two Decades after the Disaster | C38: Evangeline B. Mandia | D38: Completed | E38: 44570 | F38: 44932 | G38: 17th National Symposium of Marine Science Philippine Association of Marine Sciences (PAMS) | H38: Batangas State University, Batangas City | I38: National | J38: July 20-22, 2023.
A39: 17 | B39: Status of Implementation of Katarungang Pambarangay in Ilaya I District, Municipality of Boac, Marinduque: Basis for Intervention Program | C39: John Kenneth F. Liguit Leodegario M. Jalos, Jr. | D39: Completed | E39: 1/15/2023 | F39: 4/15/2023 | G39: 9th Regional Science and Technology Conference | H39: Marinduque State College, Tanza, Boac, Marinduque/Zoom | I39: Regional | J39: August 30-31, 2023
A40: 18 | B40: Narrative Inquiry of Teaching Reading Strategies to English Language Learners of Selected Public Elementary Teachers of Grade 6 in Boac North District: Basis for the Proposed Framework | C40: Jean Grace M. Solina-Nazareno Alissa Pamela G. Hernandez | D40: Completed | E40: 1/20/2023 | F40: 4/20/2023 | G40: 9th Regional Science and Technology Conference | H40: Marinduque State College, Tanza, Boac, Marinduque/Zoom | I40: Regional | J40: August 30-31, 2023
A41: 19 | B41: Profiling of Marinduque State College-Bachelor of Secondary Education Graduates’ Achievements | C41: Dexter M. Go Liza Marie M. Manoos-Pacia | D41: Completed | E41: 1/15/2023 | F41: 4/15/2023 | G41: 9th Regional Science and Technology Conference | H41: Marinduque State College, Tanza, Boac, Marinduque/Zoom | I41: Regional | J41: August 30-31, 2023
A42: 20 | B42: Students’ Perceptions Towards Learning Mathematics and their Academic Performances | C42: Gliza N. Almonte Liza Marie M. Manoos-Pacia | D42: Completed | E42: 1/20/2023 | F42: 4/20/2023 | G42: 9th Regional Science and Technology Conference | H42: Marinduque State College, Tanza, Boac, Marinduque/Zoom | I42: Regional | J42: August 30-31, 2023
A43: 21 | B43: The Use Of Six-Questions Cognitive Model In Developing The Mathematical Skills Of Grade 6 Learners | C43: John Cris P. Andrade Noel R. Palomares | D43: Completed | E43: 45201 | F43: 45204 | G43: 9th Regional Science and Technology Conference | H43: Marinduque State College, Tanza, Boac, Marinduque/Zoom | I43: Regional | J43: August 30-31, 2023
A44: 22 | B44: Level of Satisfaction of Bachelor of Secondary Education (Bsed) Students On The Auxiliary Services, Marinduque State College | C44: Noelle Anne S. Pelaez Liza Marie M. Manoos-Pacia | D44: Completed | E44: 1/20/2023 | F44: 4/20/2023 | G44: 9th Regional Science and Technology Conference | H44: Marinduque State College, Tanza, Boac, Marinduque/Zoom | I44: Regional | J44: August 30-31, 2023
A45: 23 | B45: Myers-Briggs Type Indicator and the Academic Performance of the Bachelor of Secondary Education Major in Mathematics | C45: Gianne Patricia M. Togonon Liza Marie M. Manoos-Pacia | D45: Completed | E45: 1/15/2023 | F45: 4/15/2023 | G45: 9th Regional Science and Technology Conference | H45: Marinduque State College, Tanza, Boac, Marinduque/Zoom | I45: Regional | J45: August 30-31, 2023
A46: 24 | B46: Sentiment Analysis of Customer Reviews in E-Commerce | C46: Pollux Rey Ronjie Mar Malinao | D46: Completed | E46: 3/20/2023 | F46: 5/20/2023 | G46: 9th Regional Science and Technology Conference | H46: Marinduque State College, Tanza, Boac, Marinduque/Zoom | I46: Regional | J46: August 30-31, 2023
A47: 25 | B47: Comprehensive Corn Leaf Disease Detection and Classification through Convolutional Neural Networks: A U-Net Based Approach for Semantic Segmentation and Performance Evaluation | C47: Jerald B. Mabuti | D47: Completed | E47: 1/25/2023 | F47: 6/25/2023 | G47: 9th Regional Science and Technology Conference | H47: Marinduque State College, Tanza, Boac, Marinduque/Zoom | I47: Regional | J47: August 30-31, 2023
A48: 26 | B48: Predictive Modeling for Carabao Milk Quality: Unraveling Key Influencers using Machine Learning Techniques | C48: Wilmer M. Pascual | D48: Completed | E48: 3/25/2023 | F48: 7/25/2023 | G48: 9th Regional Science and Technology Conference | H48: Marinduque State College, Tanza, Boac, Marinduque/Zoom | I48: Regional | J48: August 30-31, 2023
A49: 27 | B49: Butterfly Taxonomy Mapping through Convolutional Neural Network Using Resnet50 as Base Model | C49: Paulo Jose H. Marquez | D49: Completed | E49: 45200 | F49: 45205 | G49: 9th Regional Science and Technology Conference | H49: Marinduque State College, Tanza, Boac, Marinduque/Zoom | I49: Regional | J49: August 30-31, 2023
A50: 28 | B50: Utilizing Learning Style Theory in Tertiary Education: Towards Adaptive Learning | C50: Ryan Clifford L. Perez | D50: Completed | E50: 5/15/2023 | F50: 7/15/2023 | G50: 9th Regional Science and Technology Conference | H50: Marinduque State College, Tanza, Boac, Marinduque/Zoom | I50: Regional | J50: August 30-31, 2023
A51: 29 | B51: Towards An Adaptive Learning for Tertiary Education: The Potential of Universal Design For Learning (UDL) Framework | C51: Ryan Clifford L. Perez | D51: Completed | E51: 4/15/2023 | F51: 7/15/2023 | G51: 9th Regional Science and Technology Conference | H51: Marinduque State College, Tanza, Boac, Marinduque/Zoom | I51: Regional | J51: August 30-31, 2023
A52: 30 | B52: The Impact of Investment Fraud Victimization to the Well-being of Selected College Students: A Basis in Developing Interventions | C52: Ronalyn M. Motol | D52: Completed | E52: 44929 | F52: 44934 | G52: APCORE-PIKSI 2023 Hybrid International Conference | H52: Grand Asrilia Hotel Bandung, West Java Indonesia | I52: International | J52: August 29-31, 2023
A53: 31 | B53: The Marinduque State College Research and Extension Experiences through the Years: College Universityhood Program Underpinning | C53: Diosdado P. Zulueta | D53: Completed | E53: 07/15/2023 | F53: 09/15/2023 | G53: 1st International Multidisciplinary Research and Extension Conference | H53: BSC Amphitheater, Batanes State College, Batanes | I53: International | J53: September 19-22, 2023
A54: 32 | B54: Flood monitoring and warning system | C54: Edgardo R. Laririt | D54: Completed | E54: 44571 | F54: 44935 | G54: 1st RAISE Summit Live Technology Pitching – 1st Regional Research and Innovation Week | H54: Dioscoro L. Umali Hall, University of the Philippines, Los Baños, Laguna | I54: Regional | J54: 45224
A55: 33 | B55: Influence of Year and Parity on the Reproductive Performance of Markaduke Natie Pigs | C55: Joeauna L. Loto | D55: Completed | E55: 5/20/2023 | F55: 10/20/2023 | G55: ISSAAS International Scientific Congress - | H55: Acacia Hotel Manila, Alabang, Muntinlupa | I55: International | J55: November 8-10, 2023
A56: 34 | B56: Unmasking the hidden dangers: Assessing the health risk of heavy metals in the soil of Mogpog, Marinduque, Philippines | C56: Ronnel C. Nolos | D56: Completed | E56: 44930 | F56: 44935 | G56: MHRDC 12th Health Research Forum – MIMAROPA Health Research and Development Consortium | H56: Makati Palace Hotel, Manila | I56: Regional | J56: November 14-15, 2023
A57: 35 | B57: Lived Experiences of the Adults on the Causes, Sign and Symptoms, and Traditional Treatment for Balis in Selected Barangay in the Municipality of Torrijos | C57: Lovelie Ann Mataac Mark Joseph M Ricafrente | D57: Completed | E57: 45054 | F57: 45057 | G57: MHRDC 12th Health Research Forum – MIMAROPA Health Research and Development Consortium | H57: Makati Palace Hotel, Manila | I57: Regional | J57: November 14-15, 2023
A58: 36 | B58: Level of Knowledge, Attitude and Preventive Practices of Farmers Regarding Leptospirosis at Sitio Mansabang, Buliasnin Boac, Marinduque” | C58: Mariel L. Lumalang Ghien Sylveria M. Lasic Keth Allen. M. Nambio Jeannelle. B. Prieto Ma. Rose M. Vitto | D58: Completed | E58: 45054 | F58: 45057 | G58: MHRDC 12th Health Research Forum – MIMAROPA Health Research and Development Consortium | H58: Makati Palace Hotel, Manila – via Zoom | I58: Regional | J58: November 14-15, 2023
A59: 37 | B59: The Effects of “Tutok Kainan” Dietary Supplementation Program Amongst Selected 6-23 Months Children of The Municipality of Boac, Marinduque. | C59: Rhaby L. De la Cruz, Marielle Ann G. Rosales & Djoanna Izabelle L. Zoleta | D59: Completed | E59: 45053 | F59: 45057 | G59: MHRDC 12th Health Research Forum – MIMAROPA Health Research and Development Consortium | H59: Makati Palace Hotel, Manila – via Zoom | I59: Regional | J59: November 14-15, 2023
A60: 38 | B60: An Ethnobotanical Study on the Plants used by the Traditional Healers in the Selected Barangays of Gasan, Buenavista and Torrijos, Marinduque. | C60: Angela S. Canon, Joy Ann L. Majaba & Genine Ritchel M. Sales | D60: Completed | E60: 45054 | F60: 45057 | G60: MHRDC 12th Health Research Forum – MIMAROPA Health Research and Development Consortium | H60: Makati Palace Hotel, Manila – via Zoom | I60: Regional | J60: November 14-15, 2023
A61: 39 | B61: “Dapat Ganito, Dapat Ganyan”: A Comparative Analysis of Social Expectations for Males and Females | C61: Rommuel B. Luto May C. Fabrero Joshua Aaron M. Pagulayan | D61: Completed | E61: 45054 | F61: 45057 | G61: 1st National GAD Research Conference | H61: Via Zoom | I61: National | J61: November 15-17, 2023
A62: 40 | B62: My Son is Gay: Stories of Father as Parents to Homosexuals | C62: Mark John L. Rodelas Marianne Rose D. Ferrera Arnel M. Lantita | D62: Completed | E62: 07/15/2023 | F62: 10/15/2023 | G62: 1st National GAD Research Conference | H62: Via Zoom | I62: National | J62: November 15-17, 2023
A63: 41 | B63: Assessing Pre-Service Teachers’ People Skills: A Basis for Student Development Programs | C63: Willa Mae M. Paredes | D63: Completed | G63: 1st National GAD Research Conference | H63: Via Zoom | I63: National | J63: November 15-17, 2023
A64: 42 | B64: SINEsilip: Taking a look at the Marcos’ narrative in films through the years | C64: Jimely Jane Estoya | D64: Completed | E64: 44936 | F64: 44959 | G64: Communication Research International Conference (CRIC) 2023 | H64: UP Diliman, Quezon City | I64: International | J64: November 17-18, 2023
A65: 43 | B65: Being Mama: An analysis on the representation of motherhood through mom influences in Facebook video | C65: Andrea Gayle Saet | D65: Completed | E65: 44936 | F65: 44959 | G65: Communication Research International Conference (CRIC) 2023 | H65: UP Diliman, Quezon City | I65: International | J65: November 17-18, 2023
A66: 44 | B66: Student Acceptability & Comparative Analysis of the Effectiveness of the 3Es Learning Model in Skills Oriented Program | C66: Liza Marie Manoos-Pacia | D66: Completed | E66: 2/15/2023 | F66: 6/15/2023 | G66: 2nd International on Education Studies | H66: Tarlac Agricultural University – via Zoom | I66: International | J66: November 23-25, 2023
A67: 45 | B67: Establishing the Rural Urban and Rurban Profile of the Province of Marinduque towards creating a Transectoral Development Plan for the Province | C67: Anne Grace M. Labatete | D67: Completed | E67: 3/15/2023 | F67: 8/15/2023 | G67: 2023 Philippine Society for Public Administration (PSPA) | H67: Greenleaf Hotel, General Santos City | I67: International | J67: November 24-26, 2023
A68: 46 | B68: MSMEs Diagnostic Framework: Basis for Policy Development | C68: Michael V. Capiña | D68: Completed | E68: 1/25/2023 | F68: 6/25/2023 | G68: 1st International Conference on Entrepreneurship and SME Development (ICESMED) 2023 | H68: Malcom Hall, College of Law and Institute for Small Scale Industries, UP Diliman, Quezon City | I68: International | J68: November 28-29, 2023
A69: 47 | B69: Distribution of Macroinvertebrate communities in seagrass and ecotones between adjacent habitats: Evidence of coastal habitats’ linkage | C69: Regie F. Mampusti | D69: Completed | E69: 3/15/2023 | F69: 8/15/2023 | G69: 3rd International Multidisciplinary Conference on Engineering and Technology, Education, Management and Development Studies (3rd IMCETEMDS) | H69: Camarines Sur Polytechnic Colleges | I69: International | J69: November 28-29, 2023
A70: 48 | B70: Vulnerability to Climate Change of "Giant Squid" (Thysanoteuthis rhombus) Fishery in Marinduque, Philippines | C70: Paloma D. De Chavez | D70: Completed | E70: 45054 | F70: 45057 | G70: Webinar Series on the National Consortium for the Small-Scale Fisheries Research and Development or Too-Big-To-Ignore (TBTI) | H70: Via Zoom | I70: National | J70: 45260
A71: 49 | B71: Nurturing Hope and Growth: Empowering Women and Men through Nypa frutican cultivation amidst adversity in Marinduque Island Province in 2020` | C71: Doreen R. Mascareñas Harvey A. Dulay* Wilson R. Paez | D71: Completed | E71: 9/25/2023 | F71: 11/25/2023 | G71: National Gender and Development Conference and Research Forum | H71: Manila Grand Opera Hotel, Doroteo Hotel, Manila | I71: National | J71: December 4-6, 2023
A72: 50 | B72: Larval Development of Scissor River Prawn Macrobrachium latidactylus (Thallwitz, 1891) in a small hatchery in Marinduque, Philippines | C72: Doreen R. Mascareñas | D72: Completed | E72: 1/15/2023 | F72: 6/15/2023 | G72: 55th FIFMS Annual Convention | H72: Tawi-Tawi College of Technology and Oceanography (MSU-TCTO), Tawi-Tawi | I72: National | J72: December 6-8, 2023 | Q72: Seminar on the Conservation and Protection of Freshwater Prawns (Macrobrachium spp.) | R72: This activity is a result of the DOST-PCAARRD funded project on freshwater prawn hatchery which aims to capacitate the beneficiaries the necessary knowledge on how to properly culture, conserve and protect the freshwater prawns in Marinduque | S72: Samahan ng mga maghihipon sa Tabionan
A73: 51 | B73: Level of Language and Communication Proficiency of the Barangay Secretaries of the Municipality of Mogpog: Basis for Creating an Enhanced Training Guide for Language and Communication | C73: Jholey Rose L. Lancion Jerome Lingon | D73: Completed | E73: 2/20/2023 | F73: 5/20/2023 | G73: Philippine Association for Language Teaching International Conference | H73: Teacher’s Camp, Baguio City | I73: International | J73: December 7-9, 2023
A74: 52 | B74: Curriculum-Based Instructional Material for Reading and Writing Skills | C74: Ma. Jessica L. Semilla | D74: Completed | E74: 4/15/2023 | F74: 8/15/2023 | G74: Philippine Association for Language Teaching International Conference | H74: Teacher’s Camp, Baguio City | I74: International | J74: December 7-9, 2023
A75: 53 | B75: Reading Comprehension Level in English Language of the Selected Alternative Learning System Learners | C75: Jean Grace M. Solina | D75: Completed | E75: 3/20/2023 | F75: 7/20/2023 | G75: Philippine Association for Language Teaching International Conference | H75: Teacher’s Camp, Baguio City | I75: International | J75: December 7-9, 2023
A76: 54 | B76: Performance characteristics of Sacol (Kappaphycus striatum) and Spinosum (Eucheuma denticulatum) seaweed cultivars using coco coir as tying materials tested in open and cove areas in Mogpog, Marinduque | C76: Orlen M. Mallen | D76: Completed | E76: Feb. 2023 | F76: 45047 | G76: 3rd International Conference on Agriculture, Biosystems, and Technology (3rd IConABT) | H76: Tarlac Agricultural University – via Zoom | I76: International | J76: December 11-12, 2023
A77: 55 | B77: Efforts on selecting laboratory-reared seaweed cultivars and providing alternative livelihood through seaweed farming in Marinduque, Philippines | C77: Regie F. Mampusti | D77: Completed | E77: Janury 2023 | F77: 45200 | G77: 3rd International Conference on Agriculture, Biosystems, and Technology (3rd IConABT) | H77: Tarlac Agricultural University – via Zoom | I77: International | J77: December 11-12, 2023
B79: 2022
A80: 1 | B80: Practices of the MSC ESL Teachers towards Online Assessment amidst the COVID-19 Pandemic | C80: Marieneth L. Malubag | D80: Completed | E80: 44207 | F80: 44684 | G80: Linguistic Society of the Philippines International Conference 2022 & 21st English in Southeast Asia: A Joint Conference LSPIC 2022 & 21st ESEA | H80: University of Sto. Tomas – via Zoom | I80: International | J80: March 10-12, 2022
A81: 2 | B81: A Positioning Analysis on the Competing Roles of an ‘Academic’ ‘Mother’ | C81: Jholey Rose L. Lancion | D81: Completed | E81: 44327 | F81: 44684 | G81: Linguistic Society of the Philippines International Conference 2022 & 21st English in Southeast Asia: A Joint Conference LSPIC 2022 & 21st ESEA | H81: University of Sto. Tomas – via Zoom | I81: International | J81: March 10-12, 2022
A82: 3 | B82: The Position of Marinduque Tagalog in the Linguistic Landscape of the Heritage Town of Boac, Marinduque | C82: Cherie Ann M. Luna | D82: Completed | E82: 44207 | F82: 44684 | G82: Linguistic Society of the Philippines International Conference 2022 & 21st English in Southeast Asia: A Joint Conference LSPIC 2022 & 21st ESEA | H82: University of Sto. Tomas – via Zoom | I82: International | J82: March 10-12, 2022
A83: 4 | B83: Meat Quality Markers Unveil the Markaduke Native Pig as Potential Source of Premium Pork Products | C83: Arnolfo M. Monleon | D83: Completed | E83: 44326 | F83: 44684 | G83: 89th General Membership Assembly of the National Research Council of the Philippines | H83: Manila | I83: National | J83: March 15, 2022
A84: 5 | B84: MSCCA Island and Archipelagic Studies: Transition from Studies Center to Creative Hub with CCP, KWF and NCCA | C84: Randy T. Nobleza | D84: Completed | E84: 10/15/2021 | F84: 4/15/2022 | G84: 4th SOSS Research Conference | H84: Ateneo De Manila University | I84: Regional | J84: April 18-20, 2022
A85: 6 | B85: Utilizing Surveillance, Trust, and Democracy as an Online Pedagogy Amidst Pandemic 2021 | C85: Lorimer L. Imperio | D85: Completed | E85: 11/20/2021 | F85: 3/20/2022 | G85: 18th International Conference on Technology, Knowledge, and Society | H85: National Changhua University of Education Taiwan, Province of China | I85: International | J85: April 15-16-, 2022
A86: 7 | B86: Phytoremediation of Potential Toxic Elements by Native Tree Species in Mined-spoiled soils in Matraszentimre, Hungary | C86: Jovito L. Opeña | D86: Completed | E86: 1/30/2022 | F86: 4/30/2022 | G86: 6th International Symposium on Biosphere and Environmental Safety | H86: Obuda University, Budapest, Hungary | I86: International | J86: May 5-6, 2022
A87: 8 | B87: Semen Characterization of Markaduke Boars Improve Litter size production | C87: Joeauna L. Loto Giselle M. Perlas | D87: Completed | E87: 44836 | F87: 44839 | G87: 2nd International Research Conference in Sciences, Education, and Sports (IRCISES) | H87: via Zoom | I87: International | J87: May 21-23, 2022
A88: 9 | B88: Will Economic Capability and Technological Availability Affect Graduate Competencies: An Exploratory Study of BSIT/BSIS Programs this Pandemic | C88: Maria Nessa M. Solomon Ivy Joy N. Aguiflor | D88: Completed | E88: 44682 | F88: 44686 | G88: International Conference on Assessment in the New Normal (ICANN 2022) | H88: Jose Rizal Memorial State University | I88: International | J88: May 25-27, 2022
A89: 10 | B89: Carps? Ready to Face it? The Information System Students’ Readiness for F2F Classes | C89: Arben A. Ornedo | D89: Completed | E89: 44682 | F89: 44686 | G89: International Conference on Assessment in the New Normal (ICANN 2022) | H89: Jose Rizal Memorial State University | I89: International | J89: May 25-27, 2022
A90: 11 | B90: Adequacy of BS LEAD Criminalistics Laboratory: The Significance to Learning Modality and Conversion to BS Criminology | C90: Jayceron L. Monteagudo Vergel L. Mayo | D90: Completed | E90: 1/15/2022 | F90: 5/15/2022 | G90: 1st International Multidisciplinary Virtual Research Conference | H90: 1st International Multidisciplinary Virtual Research Conference | I90: International | J90: June 24-26, 2022
A91: 12 | B91: Factors Involved In The Contemporary Authenticity Of Tourist Industry In Marinduque Province | C91: Merryrose Palma Angielyn D. Marquez | D91: Completed | E91: 44835 | F91: 44840 | G91: 1st MSC Mogpog ESC Online Regional Research Conference (1st ESCORRC) | H91: Marinduque State College Audio-Visual Room via Zoom | I91: Regional | J91: June 30, 2022
A92: 13 | B92: Development, Validity And Evaluation Of Contextualized Strategic Intervention Materials (Csims) In Specific Competencies In Science 10 | C92: Jimbert S. Cedeño | D92: Completed | E92: 44682 | F92: 44686 | G92: 1st MSC Mogpog ESC Online Regional Research Conference (1st ESCORRC) | H92: Marinduque State College Audio-Visual Room via Zoom | I92: Regional | J92: June 30, 2022
A93: 14 | B93: Assessment Of The Environmental Impact Of Tourism On The Selected Natural Attractions Of Buenavista, Marinduque | C93: Merryrose Palma Diane Babes L. Dela Cruz | D93: Completed | E93: 1/20/2022 | F93: 5/20/2022 | G93: 1st MSC Mogpog ESC Online Regional Research Conference (1st ESCORRC) | H93: Marinduque State College Audio-Visual Room via Zoom | I93: Regional | J93: June 30, 2022
A94: 15 | B94: Assessment on E-Governance Implementation: Experience of the Municipality of Buenavista | C94: Anne Grace M. Labatete | D94: Completed | E94: 44835 | F94: 44840 | G94: 1st MSC Mogpog ESC Online Regional Research Conference (1st ESCORRC) | H94: Marinduque State College Audio-Visual Room via Zoom | I94: Regional | J94: June 30, 2022
A95: 16 | B95: Socio-Cultural Impacts Of Tourism As Perceived By Host Community And Tourists In Torrijos Marinduque | C95: Merryrose Palma Frecious R. Reataza | D95: Completed | E95: 44835 | F95: 44840 | G95: 1st MSC Mogpog ESC Online Regional Research Conference (1st ESCORRC) | H95: Marinduque State College Audio-Visual Room via Zoom | I95: Regional | J95: June 30, 2022
A96: 17 | B96: The Multicultural Workplace: Preparing Hotel Employees In The Municipality Of Boac | C96: Merryrose Palma Jelyn Mae S. Manahan | D96: Completed | E96: 1/20/2022 | F96: 6/20/2022 | G96: 1st MSC Mogpog ESC Online Regional Research Conference (1st ESCORRC) | H96: Marinduque State College Audio-Visual Room via Zoom | I96: Regional | J96: June 30, 2022
A97: 18 | B97: Inventory Management Practices of Selected Cooperatives in Buenavista and Mogpog, Marinduque | C97: Mark Rey U. Tan Maeflor M. Loto, Margie P. Fatalla | D97: Completed | E97: 44682 | F97: 44686 | G97: 1st MSC Mogpog ESC Online Regional Research Conference (1st ESCORRC) | H97: Marinduque State College Audio-Visual Room via Zoom | I97: Regional | J97: June 30, 2022
A98: 19 | B98: The Perception Of The Selected Penitentes In New Normal Of Moriones Lenten Rites In Boac | C98: Merryrose Palma Joemel R. Ormacido | D98: Completed | E98: 1/20/2022 | F98: 5/20/2022 | G98: 1st MSC Mogpog ESC Online Regional Research Conference (1st ESCORRC) | H98: Marinduque State College Audio-Visual Room via Zoom | I98: Regional | J98: June 30, 2022
A99: 20 | B99: Inventory Management Practices of Selected Business Establishments in Boac and Mogpog, Marinduque | C99: Mark Rey U. Tan Bernadette M. Magaling, John Lester M. Manuba, Hajji Rod M. Ola | D99: Completed | E99: 44563 | F99: 44567 | G99: 1st MSC Mogpog ESC Online Regional Research Conference (1st ESCORRC) | H99: Marinduque State College Audio-Visual Room via Zoom | I99: Regional | J99: June 30, 2022
A100: 21 | B100: Impacts Of Local Traveling In Selected Destinations In The Municipality Of Mogpog, Marinduque During The "New Normal” | C100: Merryrose Palma Kayla Monic J. del Mundo | D100: Completed | E100: 44682 | F100: 44686 | G100: 1st MSC Mogpog ESC Online Regional Research Conference (1st ESCORRC) | H100: Marinduque State College Audio-Visual Room via Zoom | I100: Regional | J100: June 30, 2022
A101: 22 | B101: Credit Risk Management Practices Of Selected Cooperatives In Marinduque | C101: Mark Glenn M. Mamugay, Elizabeth J. Bundalian, Alaiza M. Eclavea, Carrel Sadiwa, Aira A. Linga, Michael Jaye P. Ribleza | D101: Completed | E101: 44563 | F101: 44567 | G101: 1st MSC Mogpog ESC Online Regional Research Conference (1st ESCORRC) | H101: Marinduque State College Audio-Visual Room via Zoom | I101: Regional | J101: June 30, 2022
A102: 23 | B102: Impacts Of The Pandemic On The Livelihoods Of Beach Resort Tourism Workers In Boac, Marinduque | C102: Merryrose Palma Marife R. Laman | D102: Completed | E102: 44563 | F102: 44567 | G102: 1st MSC Mogpog ESC Online Regional Research Conference (1st ESCORRC) | H102: Marinduque State College Audio-Visual Room via Zoom | I102: Regional | J102: June 30, 2022
A103: 24 | B103: Narratives About Cave Of Filipino Guerrillas In Pili, Mogpog, Marinduque | C103: Michael V. Capina | D103: Completed | E103: 1/25/2022 | F103: 5/25/2022 | G103: 1st MSC Mogpog ESC Online Regional Research Conference (1st ESCORRC) | H103: Marinduque State College Audio-Visual Room via Zoom | I103: Regional | J103: June 30, 2022
...

Sheet Extension Program (Op1&Op3)
B1: NAME OF INSTITUTION: | C1: (MARINDUQUE STATE COLLEGE)
B2: PROGRAM: | C2: TECHNICAL ADVISORY EXTENSION PROGRAM
B3: INDICATOR/S: | C3: Output Indicator 1: Number of trainees weighted by the length of training Output Indicator 3: Percentage of beneficiaries who rate the training course/s as satisfactory or higher in terms of quality and relevance
B4: INSTRUCTIONS: | C4: In Column 1, list all training programs/activities of extension programs conducted within the year. Indicate the inclusive dates for each training program in Column 2. In Column 3 Input the duration of each training program in hours. The Weights per Duration column is computed automatically. Please do not overwrite any cell in this column. For each program, input the number of trainees who attended in Column 4. Column 5 is computed automatically. Please do not overwrite any cell in this column. In Column 6 and Column 7, encode the number of trainees surveyed towards the quality and relevance of the training program attended.
B5: REFERENCES: | C5: Output Indicator 1 : Number of trainees weighted by the length of training Output Indicator 3 : Percentage of beneficiaries who rate the training course/s as satisfactory or higher in terms of quality and relevance
B6: MEANS OF VERIFICATION: | C6: 1) Training program 2) Attendance sheets 3) Reports / other documentations 4) Sample of accomplished satisfaction survey
B7: LINK TO GOOGLE DRIVE FOLDER: | C7: (https://drive.google.com/drive/folders/1Zezs1rJYwXox2umra5r2TT9W34aBuL09?usp=drive_link)
A9: SAMPLE
A10: 1 | C10: 2 | E10: 3 | G10: 4 | H10: 5 | I10: 6 | J10: 7
A11: Title of Training | C11: Inclusive Dates | E11: Duration in Terms of Number of Hours | F11: Weight per Duration | G11: Number of Trainees | H11: Number of Trainees x Weight per Duration | I11: Number of Trainees Surveyed | J11: Quality and Relevance Rating
C12: Start Date (MMM-DD-YYYY) | D12: End Date (MMM-DD-YYYY) | J12: 1 | K12: 2 | L12: 3 | M12: 4 | N12: 5
J13: P | K13: F | L13: S | M13: VS | N13: E
A14: 1 | B14: Community and Training Needs Assessment | C14: 44975 | D14: 44975 | E14: 4 | F14: 0.5 | G14: 25 | H14: {=F14:F18*G14:G18} -> 12.5 | I14: 25 | M14: 5 | N14: 20
A15: 2 | B15: Hands-on Training on Trichoderma Prodcution and Application | C15: 44989 | D15: 44996 | E15: 8 | F15: 1 | G15: 25 | H15: 25 | I15: 25 | M15: 6 | N15: 19
A16: 3 | B16: Hands-on Training on Table Skirting and Paper Mache | C16: 45052 | D16: 45073 | E16: 16 | F16: 1.25 | G16: 30 | H16: 37.5 | I16: 25 | K16: 1 | L16: 1 | M16: 4 | N16: 19
A17: 4 | B17: Training on Harvesting, Post-harvest handling, and Processing of Coffee | C17: 45080 | D17: 45129 | E17: 28 | F17: 1.5 | G17: 40 | H17: 60 | I17: 26 | K17: 1 | L17: 2 | M17: 12 | N17: 11
A18: 5 | B18: Agri-Financial Management and Literacy Training | C18: 45122 | D18: 45157 | E18: 48 | F18: 2 | G18: 26 | H18: 52 | I18: 26 | L18: 5 | M18: 9 | N18: 12
A20: 1 | C20: 2 | E20: 3 | G20: 4 | H20: 5 | I20: 6 | J20: 7
A21: Title of Training | C21: Inclusive Dates | E21: Duration in Terms of Number of Hours | F21: Weight per Duration | G21: Number of Trainees | H21: Number of Trainees x Weight per Duration | I21: Number of Trainees Surveyed | J21: Quality and Relevance Rating
C22: Start Date (MMM-DD-YYYY) | D22: End Date (MMM-DD-YYYY) | J22: 1 | K22: 2 | L22: 3 | M22: 4 | N22: 5
J23: P | K23: F | L23: S | M23: VS | N23: E
F24: =IFS(E24="","",E24>=40,"2",E24>=24,"1.5",E24>=16,"1.25",E24>=8,"1",E24<8,"0.5") -> #NAME? | H24: =G24*F24 -> #NAME?
A25: {=IFERROR(SEQUENCE(COUNTA(B25:B68)),1)} -> 1 | B25: The eSalba for Disaster and Health Risks Reduction | C25: 44957 | D25: 44959 | E25: 24 | F25: =IFS(E25="","",E25>=40,"2",E25>=24,"1.5",E25>16,"1.25",E25>=8,"1",E25<8,"0.5") -> #NAME? | G25: 465 | H25: =G25*F25 -> #NAME? | I25: 465 | J25: 0 | K25: 0 | L25: 0 | M25: 75 | N25: 390
A26: 2 | B26: Asian Waterbird Census 2023 | C26: 44950 | D26: 44953 | E26: 24 | F26: =IFS(E26="","",E26>=40,"2",E26>=24,"1.5",E26>16,"1.25",E26>=8,"1",E26<8,"0.5") -> #NAME? | G26: 61 | H26: =G26*F26 -> #NAME? | I26: 61 | J26: 0 | K26: 0 | L26: 0 | M26: 23 | N26: 38
A27: 3 | B27: Regular Protected Area Management Board (PAMB) of the Marinduque Wildlife Sactuary (MWS) Meeting | C27: 44980 | D27: 44980 | E27: 8 | F27: =IFS(E27="","",E27>=40,"2",E27>=24,"1.5",E27>16,"1.25",E27>=8,"1",E27<8,"0.5") -> #NAME? | G27: 51 | H27: =G27*F27 -> #NAME? | I27: 51 | J27: 0 | K27: 0 | L27: 0 | M27: 5 | N27: 46
A28: 4 | B28: Shing-A-ling Snack: Product Innovation & Marketing Strategies | C28: 44985 | D28: 44985 | E28: 8 | F28: =IFS(E28="","",E28>=40,"2",E28>=24,"1.5",E28>16,"1.25",E28>=8,"1",E28<8,"0.5") -> #NAME? | G28: 119 | H28: =G28*F28 -> #NAME? | I28: 119 | J28: 0 | K28: 0 | L28: 0 | M28: 24 | N28: 95
A29: 5 | B29: Distribution of Farm Materials to Seaweed Farmers | C29: 44988 | D29: 44988 | E29: 8 | F29: =IFS(E29="","",E29>=40,"2",E29>=24,"1.5",E29>16,"1.25",E29>=8,"1",E29<8,"0.5") -> #NAME? | G29: 34 | H29: =G29*F29 -> #NAME? | I29: 34 | J29: 0 | K29: 0 | L29: 0 | M29: 5 | N29: 29
A30: 6 | B30: Micro-Enterprise Development Training | C30: 44998 | D30: 44998 | E30: 8 | F30: =IFS(E30="","",E30>=40,"2",E30>=24,"1.5",E30>16,"1.25",E30>=8,"1",E30<8,"0.5") -> #NAME? | G30: 94 | H30: =G30*F30 -> #NAME? | I30: 94 | J30: 0 | K30: 0 | L30: 0 | M30: 35 | N30: 59
A31: 7 | B31: Marinduque Bamboo Industry Development Council Reorganization and 1st Quarter Meeting for 2023 | C31: 45000 | D31: 45000 | E31: 8 | F31: =IFS(E31="","",E31>=40,"2",E31>=24,"1.5",E31>16,"1.25",E31>=8,"1",E31<8,"0.5") -> #NAME? | G31: 21 | H31: =G31*F31 -> #NAME? | I31: 21 | J31: 0 | K31: 0 | L31: 0 | M31: 8 | N31: 13
A32: 8 | B32: Consultative Meeting on the Status of Bagumbungan Cave | C32: 45001 | D32: 45001 | E32: 8 | F32: =IFS(E32="","",E32>=40,"2",E32>=24,"1.5",E32>16,"1.25",E32>=8,"1",E32<8,"0.5") -> #NAME? | G32: 13 | H32: =G32*F32 -> #NAME? | I32: 13 | J32: 0 | K32: 0 | L32: 0 | M32: 0 | N32: 13
A33: 9 | B33: Consultative Meeting on the Status of Bagumbungan Cave | C33: 45008 | D33: 45008 | E33: 8 | F33: =IFS(E33="","",E33>=40,"2",E33>=24,"1.5",E33>16,"1.25",E33>=8,"1",E33<8,"0.5") -> #NAME? | G33: 10 | H33: =G33*F33 -> #NAME? | I33: 10 | J33: 0 | K33: 0 | L33: 0 | M33: 0 | N33: 10
A34: 10 | B34: Technology Forum and Workshop on New Trends in Agribusiness for Federation of Mogpog Association | C34: 45009 | D34: 45009 | E34: 8 | F34: =IFS(E34="","",E34>=40,"2",E34>=24,"1.5",E34>16,"1.25",E34>=8,"1",E34<8,"0.5") -> #NAME? | G34: 50 | H34: =G34*F34 -> #NAME? | I34: 50 | J34: 0 | K34: 0 | L34: 0 | M34: 11 | N34: 39
A35: 11 | B35: 1ST CY 2023 TWG on Resource Management Meeting cum Orientation on the Formation of Watershed Management Council (WMC) | C35: 45012 | D35: 45012 | E35: 8 | F35: =IFS(E35="","",E35>=40,"2",E35>=24,"1.5",E35>16,"1.25",E35>=8,"1",E35<8,"0.5") -> #NAME? | G35: 16 | H35: =G35*F35 -> #NAME? | I35: 16 | J35: 0 | K35: 0 | L35: 0 | M35: 0 | N35: 16
A36: 12 | B36: Roll-out of the River Basin Integrated Information System (RBIIMS) | C36: 45013 | D36: 45014 | E36: 16 | F36: 1.25 | G36: 22 | H36: =G36*F36 -> 27.5 | I36: 22 | J36: 0 | K36: 0 | L36: 0 | M36: 3 | N36: 19
A37: 13 | B37: 2nd Quarter Protected PAMB En Banc Meeting of Marinduque Wildlife Sanctuary - Protected Area Management Board (MWS-PAMB) | C37: 45043 | D37: 45043 | E37: 8 | F37: =IFS(E37="","",E37>=40,"2",E37>=24,"1.5",E37>16,"1.25",E37>=8,"1",E37<8,"0.5") -> #NAME? | G37: 42 | H37: =G37*F37 -> #NAME? | I37: 42 | J37: 0 | K37: 0 | L37: 0 | M37: 7 | N37: 35
A38: 14 | B38: Planning Workshop for the Proposed Agri-Ecotourism Farm | C38: 45043 | D38: 45044 | E38: 8 | F38: 1 | G38: 53 | H38: =G38*F38 -> 53 | I38: 53 | J38: 0 | K38: 0 | L38: 0 | M38: 11 | N38: 42
A39: 15 | B39: Empowering Groups' Leadership Skills Training; Partner | C39: 45049 | D39: 45049 | E39: 8 | F39: =IFS(E39="","",E39>=40,"2",E39>=24,"1.5",E39>16,"1.25",E39>=8,"1",E39<8,"0.5") -> #NAME? | G39: 22 | H39: =G39*F39 -> #NAME? | I39: 22 | J39: 0 | K39: 0 | L39: 0 | M39: 2 | N39: 20
A40: 16 | B40: Capacity Enhancement Training on Fruit and Vegetable Drying using Electric Dehydrator Machine with Orientation and Workshop on Food Safety | C40: 45056 | D40: 45057 | E40: 16 | F40: 1.25 | G40: 60 | H40: =G40*F40 -> 75 | I40: 60 | J40: 0 | K40: 0 | L40: 0 | M40: 15 | N40: 45
A41: 17 | B41: Marinduque Wildlife Sanctuary - Protected Area Management Board (MWS) -PAMB Special Meeting | C41: 45069 | D41: 45069 | E41: 8 | F41: =IFS(E41="","",E41>=40,"2",E41>=24,"1.5",E41>16,"1.25",E41>=8,"1",E41<8,"0.5") -> #NAME? | G41: 38 | H41: =G41*F41 -> #NAME? | I41: 38 | J41: 0 | K41: 0 | L41: 0 | M41: 12 | N41: 26
A42: 18 | B42: Seminar on the Conservation and Protection of Freshwater Prawns (Macrobrachium spp.) | C42: 45070 | D42: 45070 | E42: 16 | F42: 1.25 | G42: 30 | H42: =G42*F42 -> 37.5 | I42: 30 | J42: 0 | K42: 0 | L42: 0 | M42: 13 | N42: 17
A43: 19 | B43: Masaganang Agrikultura, Maunlad na Ekonomiya | C43: 45072 | D43: 45072 | E43: 8 | F43: =IFS(E43="","",E43>=40,"2",E43>=24,"1.5",E43>16,"1.25",E43>=8,"1",E43<8,"0.5") -> #NAME? | G43: 54 | H43: =G43*F43 -> #NAME? | I43: 54 | J43: 0 | K43: 0 | L43: 0 | M43: 20 | N43: 34
A44: 20 | B44: Regional Monitoring and Validation of the Nipa Stands in Marinduque Under DENR-MSC ENGP | C44: 45083 | D44: 45084 | E44: 16 | F44: 1.25 | G44: 17 | H44: =G44*F44 -> 21.25 | I44: 17 | J44: 0 | K44: 0 | L44: 0 | M44: 0 | N44: 17
A45: 21 | B45: Coastal Clean up and Tree Planting in Celebration of World Ocean Day and Coral Triangle Day | C45: 45086 | D45: 45086 | E45: 8 | F45: 1 | G45: 53 | H45: =G45*F45 -> 53 | I45: 53 | J45: 0 | K45: 0 | L45: 0 | M45: 7 | N45: 46
A46: 22 | B46: Training on Free-Range Chicken Production and Management | C46: 45091 | D46: 45092 | E46: 16 | F46: 1.25 | G46: 66 | H46: =G46*F46 -> 82.5 | I46: 66 | J46: 0 | K46: 0 | L46: 0 | M46: 23 | N46: 43
A47: 23 | B47: Rapid Assessment of Cave | C47: 45091 | D47: 45093 | E47: 24 | F47: =IFS(E47="","",E47>=40,"2",E47>=24,"1.5",E47>16,"1.25",E47>=8,"1",E47<8,"0.5") -> #NAME? | G47: 13 | H47: =G47*F47 -> #NAME? | I47: 13 | J47: 0 | K47: 0 | L47: 0 | M47: 0 | N47: 13
A48: 24 | B48: Meeting for the Sub-Agreement re. GMAP Marinduque | C48: 45098 | D48: 45098 | E48: 8 | F48: =IFS(E48="","",E48>=40,"2",E48>=24,"1.5",E48>16,"1.25",E48>=8,"1",E48<8,"0.5") -> #NAME? | G48: 35 | H48: =G48*F48 -> #NAME? | I48: 35 | J48: 0 | K48: 0 | L48: 0 | M48: 9 | N48: 26
A49: 25 | B49: Refresher Course for the Effective Management of Marinduque Wildlife Sanctuary for PAMB Members, PAMO and TSD Staff | C49: 45098 | D49: 45100 | E49: 24 | F49: =IFS(E49="","",E49>=40,"2",E49>=24,"1.5",E49>16,"1.25",E49>=8,"1",E49<8,"0.5") -> #NAME? | G49: 207 | H49: 310.5 | I49: 207 | J49: 0 | K49: 0 | L49: 0 | M49: 32 | N49: 175
A50: 26 | B50: Special PCAT Meeting | C50: 45106 | D50: 45106 | E50: 8 | F50: =IFS(E50="","",E50>=40,"2",E50>=24,"1.5",E50>16,"1.25",E50>=8,"1",E50<8,"0.5") -> #NAME? | G50: 15 | H50: =G50*F50 -> #NAME? | I50: 15 | J50: 0 | K50: 0 | L50: 0 | M50: 0 | N50: 15
A51: 27 | B51: Training on Bamboo Propagation and Production | C51: 45134 | D51: 45135 | E51: 8 | F51: 1 | G51: 18 | H51: =G51*F51 -> 18 | I51: 18 | J51: 0 | K51: 0 | L51: 0 | M51: 8 | N51: 10
A52: 28 | B52: Project Orientation and Strategic Planning (Arrowroot Project) | C52: 45147 | D52: 45147 | E52: 8 | F52: =IFS(E52="","",E52>=40,"2",E52>=24,"1.5",E52>16,"1.25",E52>=8,"1",E52<8,"0.5") -> #NAME? | G52: 22 | H52: =G52*F52 -> #NAME? | I52: 22 | J52: 0 | K52: 0 | L52: 0 | M52: 7 | N52: 15
A53: 29 | B53: Focus Group Discussion Biodiversity Monitoring System, Marinduque Wildlife Sanctuary | C53: 45148 | D53: 45148 | E53: 8 | F53: =IFS(E53="","",E53>=40,"2",E53>=24,"1.5",E53>16,"1.25",E53>=8,"1",E53<8,"0.5") -> #NAME? | G53: 17 | H53: =G53*F53 -> #NAME? | I53: 17 | J53: 0 | K53: 0 | L53: 0 | M53: 0 | N53: 17
A54: 30 | B54: Technology Training on Free Range Chicken Production and Management | C54: 45155 | D54: 45156 | E54: 16 | F54: 1.25 | G54: 44 | H54: =G54*F54 -> 55 | I54: 44 | J54: 0 | K54: 0 | L54: 0 | M54: 11 | N54: 33
A55: 31 | B55: Site/Land Preparation Activities | C55: 45155 | D55: 45156 | E55: 16 | F55: 1.25 | G55: 21 | H55: =G55*F55 -> 26.25 | I55: 21 | J55: 0 | K55: 0 | L55: 0 | M55: 0 | N55: 21
A56: 32 | B56: Planting Activities | C56: 45161 | D56: 45163 | E56: 24 | F56: =IFS(E56="","",E56>=40,"2",E56>=24,"1.5",E56>16,"1.25",E56>=8,"1",E56<8,"0.5") -> #NAME? | G56: 77 | H56: =G56*F56 -> #NAME? | I56: 77 | J56: 0 | K56: 0 | L56: 0 | M56: 21 | N56: 56
A57: 33 | B57: Third Protected Area Management Board (PAMB) of the Marinduque Wildlife Sanctuary (MWS) Meeting | C57: 45162 | D57: 45162 | E57: 8 | F57: =IFS(E57="","",E57>=40,"2",E57>=24,"1.5",E57>16,"1.25",E57>=8,"1",E57<8,"0.5") -> #NAME? | G57: 54 | H57: =G57*F57 -> #NAME? | I57: 54 | J57: 0 | K57: 0 | L57: 0 | M57: 5 | N57: 49
A58: 34 | B58: Native Pig Program Terminal Review Meeting | C58: 45169 | D58: 45169 | E58: 8 | F58: =IFS(E58="","",E58>=40,"2",E58>=24,"1.5",E58>16,"1.25",E58>=8,"1",E58<8,"0.5") -> #NAME? | G58: 11 | H58: =G58*F58 -> #NAME? | I58: 11 | J58: 0 | K58: 0 | L58: 0 | M58: 0 | N58: 11
A59: 35 | B59: Report of Profiling | C59: 8/14, 21, & 22, 2023 | D59: 8/14, 21, & 22, 2023 | E59: 24 | F59: =IFS(E59="","",E59>=40,"2",E59>=24,"1.5",E59>16,"1.25",E59>=8,"1",E59<8,"0.5") -> #NAME? | G59: 75 | H59: =G59*F59 -> #NAME? | I59: 75 | J59: 0 | K59: 0 | L59: 0 | M59: 22 | N59: 53
A60: 36 | B60: Community Outreach | C60: 8/30-31/2023 | D60: 8/30-31/2023 | E60: 16 | F60: 1.25 | G60: 100 | H60: =G60*F60 -> 125 | I60: 100 | J60: 0 | K60: 0 | L60: 0 | M60: 29 | N60: 71
A61: 37 | B61: Entrepreneurial Mind Setting and Behavior Training | C61: 45190 | D61: 45191 | E61: 16 | F61: 1.25 | G61: 20 | H61: =G61*F61 -> 25 | I61: 20 | J61: 0 | K61: 0 | L61: 0 | M61: 5 | N61: 15
A62: 38 | B62: Training Workshop on Financial Literacy | C62: 45196 | D62: 45197 | E62: 16 | F62: 1.25 | G62: 85 | H62: =G62*F62 -> 106.25 | I62: 85 | J62: 0 | K62: 0 | L62: 0 | M62: 20 | N62: 65
A63: 39 | B63: Capacity Building of the Protected Area Management Office- Marrinduque Wildlife Sanctuary (PAMO-MWS) PAMB Members, PAMO and TSD Staff/ Personnel | C63: 45198 | D63: 45199 | E63: 16 | F63: 1.25 | G63: 17 | H63: =G63*F63 -> 21.25 | I63: 17 | J63: 0 | K63: 0 | L63: 0 | M63: 0 | N63: 17
A64: 40 | B64: Capacity-Building Training “Start-Up Success: Nurturing an Entrepreneurial Mindset and Embodying Core Values” | C64: 45222 | D64: 45222 | E64: 8 | F64: =IFS(E64="","",E64>=40,"2",E64>=24,"1.5",E64>16,"1.25",E64>=8,"1",E64<8,"0.5") -> #NAME? | G64: 76 | H64: =G64*F64 -> #NAME? | I64: 76 | J64: 0 | K64: 0 | L64: 0 | M64: 20 | N64: 56
A65: 41 | B65: Free range chicken production | C65: 45247 | D65: 45248 | E65: 16 | F65: 1.25 | G65: 40 | H65: =G65*F65 -> 50 | I65: 40 | J65: 0 | K65: 0 | L65: 0 | M65: 8 | N65: 32
A66: 42 | B66: Capacitating Educators in Research Areas and Challenges | C66: 45269 | D66: 45269 | E66: 16 | F66: 1.25 | G66: 280 | H66: =G66*F66 -> 350 | I66: 280 | J66: 0 | K66: 0 | L66: 0 | M66: 45 | N66: 235
A67: 43 | B67: Arrowroot Plantation and Management Training | C67: 45212 | D67: 45212 | E67: 8 | F67: =IFS(E67="","",E67>=40,"2",E67>=24,"1.5",E67>16,"1.25",E67>=8,"1",E67<8,"0.5") -> #NAME? | G67: 24 | H67: =G67*F67 -> #NAME? | I67: 24 | J67: 0 | K67: 0 | L67: 0 | M67: 5 | N67: 19
A68: 44 | B68: Processing Productin of Arrowroot Bagasse Pastries Chewy Cookies and Brownies | C68: 45254 | D68: 45254 | E68: 24 | F68: 1.5 | G68: 15 | H68: =G68*F68 -> 22.5 | I68: 15 | J68: 0 | K68: 0 | L68: 0 | M68: 3 | N68: 12
E69: OVERALL | G69: =SUM(G25:G68) -> 2657 | H69: =SUM(H25:H68) -> #NAME? | I69: =SUM(I24:I68) -> 2657 | J69: 0 | K69: 0 | L69: 0 | M69: =SUM(M25:M68) -> 549 | N69: =SUM(N25:N68) -> 2108
J70: =SUM(M69:N69)/I69 -> 1
A72: Prepared by:
B75: Dr. MA. EDELWINA M. BLASÉ | C75: 45348
B76: Vice President for Research, Development, Extension and Training | C76: Date
A79: Approved:
B82: Prof. DIOSDADO P. ZULUETA, DPA | C82: 45348
B83: SUC President III | C83: Date

Sheet Extension Program (Op2)
A1: NAME OF INSTITUTION: | B1: (MARINDUQUE STATE COLLEGE)
A2: PROGRAM: | B2: TECHNICAL ADVISORY EXTENSION PROGRAM
A3: INDICATOR/S: | B3: Output Indicator 2: Number of extension programs organized and supported consistent with the SUC's mandated and priority programs
A4: INSTRUCTIONS: | B4: In Column 1, list down the mandated/priority degree programs with extension programs. In Column 2, indicate the title of active extension programs aligned with Column 1. Provide the effective period of extension programs in Column 3.
A5: REFERENCES: | B5: Output Indicator 2 : Number of extension programs organized and supported consistent with the SUC's mandated and priority programs
A6: MEANS OF VERIFICATION: | B6: 1) Extension reports describing the program framework and actual implementation 2) MOUs/MOAs
A7: LINK TO GOOGLE DRIVE FOLDER: | B7: (https://drive.google.com/drive/folders/1Zezs1rJYwXox2umra5r2TT9W34aBuL09?usp=drive_link)
A9: SAMPLE
A10: 1 | B10: 2 | D10: 3
A11: Mandated / Priority Program/s | B11: Extension Program | D11: Start Date (MMM-DD-YYYY) | E11: End Date (MMM-DD-YYYY)
A12: Bachelor of Science in Agriculture; Bachelor of Science in Agribusiness | B12: 1 | C12: Processing of Coffee | D12: 44970 | E12: 45334
A13: Bachelor of Science in Agribusiness | B13: 2 | C13: Agri-Financial Management and Literacy Training | D13: 45122 | E13: 45157
A14: Bachelor of Science in Industrial Technology; Bachelor of Science in Business Administration | B14: 3 | C14: Utilization of Technology in Small Businesses | D14: 44928 | E14: 45291
A15: Bachelor of Science in Information Technology | B15: 4 | C15: Computer Literacy Campaign in Barangays | D15: 45170 | E15: 45260
A16: Bachelor of Science in Business Administration | B16: 5 | C16: Training Series for Local Entrepreneurs | D16: 45200 | E16: 45291
A18: 1 | B18: 2 | D18: 3
A19: Mandated / Priority Program/s | B19: Extension Program | D19: Start Date (MMM-DD-YYYY) | E19: End Date (MMM-DD-YYYY)
A20: Bachelor of Science in Civil Engineering | B20: 1 | C20: The eSalba for Disaster and Health Risks Reduction | D20: 44957 | E20: 44959
A21: Bachelor of Science in Food Technology | B21: 2 | C21: Capacity Enhancement Training on Fruit and Vegetable Drying using Electric Dehydrator Machine with Orientation and Workshop on Food Safety | D21: 45056 | E21: 45057
A22: Bachelor of Science in Agriculture | B22: 3 | C22: Technology Training on Free Range Chicken Production and Management | D22: 45155 | E22: 45156
A23: MAED in Educational Management | B23: 4 | C23: Capacitating Educators in Research Areas and Challenges | D23: 45269 | E23: 45269
A24: Bachelor of Science in Entrepreneurship | B24: 5 | C24: Processing Production of Arrowroot Bagasse Pastries Chewy Cookies and Brownies | D24: 45254 | E24: 45254
A26: Total Number of Extension Programs: | C26: 5
A28: Prepared by:
A31: Dr. MA. EDELWINA M. BLASÉ | C31: 45348
A32: Vice President for Research, Development, Extension and Training | C32: Date
A35: Approved:
A38: Prof. DIOSDADO P. ZULUETA, DPA | C38: 45348
A39: SUC President III | C39: Date

Sheet Extension Program (Oc)
A1: NAME OF INSTITUTION: | C1: (MARINDUQUE STATE COLLEGE)
A2: PROGRAM: | C2: TECHNICAL ADVISORY EXTENSION PROGRAM
A3: INDICATOR/S: | C3: Outcome Indicator 1: Number of active partnerships with LGUs, industries, NGOs, NGAs, SMEs, and other stakeholders as a result of extension activities.
A4: INSTRUCTIONS: | C4: In Column 1, list down agencies or industries engaged in active partnership with the institution. Aligned with Column 1, provide the titles of active extension programs in Column 2. In Column 3, input the inclusive dates of each extension program.
A5: REFERENCES: | C5: Outcome Indicator : Number of active partnerships with LGUs, industries, NGA, SMEs, and other stakeholders as a result of extension activities
A6: MEANS OF VERIFICATION: | C6: 1) Extension reports 2) MOUs/MOAs 3) Certification from SME, NGA, industries, other stakeholders
A7: LINK TO GOOGLE DRIVE FOLDER: | C7: (https://drive.google.com/drive/folders/1Zezs1rJYwXox2umra5r2TT9W34aBuL09?usp=drive_link)
A10: 1 | C10: 2 | D10: 3
A11: Partner LGU /Community/ Industry / SMEs / Private or Public Agencies / NGOs | C11: Extension Program / Activities | D11: Start Date (MMM-DD-YYYY) | E11: End Date (MMM-DD-YYYY)
A12: 1 | B12: Local Farmers of Barangay A | C12: Training on Harvesting, Post-harvest handling, and Processing of Coffee | D12: 44247 | E12: 44247
A13: 2 | B13: Barangay Official and SK Federation of Barangay A | C13: Hands on Training on Table skirting and paper mache | D13: 44247 | E13: 44247
A14: 3 | B14: Landbank of the Philippines Foundation Incorporated; Local Farmers of Barangay B; Local Farmers of Barangay C; Local Government Unit of the Municipality of ABC | C14: Financial Literacy Outreach Program for Farmers | D14: 44986 | E14: 45352
A16: 1 | C16: 2 | D16: 3
A17: Partner LGU /Community/ Industry / SMEs / Private or Public Agencies / NGOs | C17: Extension Program / Activities | D17: Start Date (MMM-DD-YYYY) | E17: End Date (MMM-DD-YYYY)
A18: {=IFERROR(SEQUENCE(COUNTA(B18:B90)),1)} -> 1 | B18: LGU Boac | C18: The eSalba for Disaster and Health Risks Reduction | D18: 44957 | E18: 44959
C19: Masaganang Agrikultura, Maunlad na Ekonomiya | D19: 45072 | E19: 45072
C20: Consultative Meeting on the Status of Bagumbungan Cave | D20: 45001 | E20: 45001
A21: 2 | B21: LGU Gasan | C21: The eSalba for Disaster and Health Risks Reduction | D21: 44957 | E21: 44959
C22: Distribution of Farm Materials to Seaweed Farmers | D22: 44988 | E22: 44988
C23: Consultative Meeting on the Status of Bagumbungan Cave | D23: 45001 | E23: 45001
A24: 3 | B24: LGU Mogpog, | C24: The eSalba for Disaster and Health Risks Reduction | D24: 44957 | E24: 44959
C25: Consultative Meeting on the Status of Bagumbungan Cave | D25: 45001 | E25: 45001
A26: 4 | B26: LGU Torrijos | C26: The eSalba for Disaster and Health Risks Reduction | D26: 44957 | E26: 44959
C27: Consultative Meeting on the Status of Bagumbungan Cave | D27: 45001 | E27: 45001
A28: 5 | B28: LGU Buenavista | C28: The eSalba for Disaster and Health Risks Reduction | D28: 44957 | E28: 44959
C29: Consultative Meeting on the Status of Bagumbungan Cave | D29: 45001 | E29: 45001
C30: Capacity-Building Training “Start-Up Success: Nurturing an Entrepreneurial Mindset and Embodying Core Values” | D30: 45222 | E30: 45222
A31: 6 | B31: LGU Sta. Cruz, | C31: The eSalba for Disaster and Health Risks Reduction | D31: 44957 | E31: 44959
C32: Consultative Meeting on the Status of Bagumbungan Cave | D32: 45001 | E32: 45001
C33: Consultative Meeting on the Status of Bagumbungan Cave | D33: 45008 | E33: 45008
C34: Planning Workshop for the Proposed Agri-Ecotourism Farm | D34: 45043 | E34: 45044
A35: 7 | B35: MAPUA | C35: The eSalba for Disaster and Health Risks Reduction | D35: 44957 | E35: 44959
A36: 8 | B36: Farmer Association | C36: Free range chicken production | D36: 45227 | E36: 45227
C37: Free range chicken production | D37: 45248 | E37: 45227
A38: 9 | B38: DENR | C38: Asian Waterbird Census 2023 | D38: 44950 | E38: 44950
C39: Consultative Meeting on the Status of Bagumbungan Cave | D39: 45001 | E39: 45001
C40: Consultative Meeting on the Status of Bagumbungan Cave | D40: 45008 | E40: 45008
C41: 2nd Quarter Protected PAMB En Banc Meeting of Marinduque Wildlife Sanctuary - Protected Area Management Board (MWS-PAMB) | D41: 45043 | E41: 45043
C42: Regular Protected Area Management Board (PAMB) of the Marinduque Wildlife Sactuary (MWS) Meeting | D42: 44980 | E42: 44980
C43: Regional Monitoring and Validation of the Nipa Stands in Marinduque Under DENR-MSC ENGP | D43: 45083 | E43: 45084
C44: Coastal Clean up and Tree Planting in Celebration of World Ocean Day and Coral Triangle Day | D44: 45086 | E44: 45086
C45: Rapid Assessment of Cave | D45: 45091 | E45: 45093
C46: Meeting for the Sub-Agreement re. GMAP Marinduque | D46: 45098 | E46: 45098
C47: Refresher Course for the Effective Management of Marinduque Wildlife Sanctuary for PAMB Members, PAMO and TSD Staff | D47: 45098 | E47: 45100
C48: Special PCAT Meeting | D48: 45106 | E48: 45106
C49: Focus Group Discussion Biodiversity Monitoring System, Marinduque Wildlife Sanctuary | D49: 45148 | E49: 45148
C50: Third Protected Area Management Board (PAMB) of the Marinduque Wildlife Sanctuary (MWS) Meeting | D50: 45162 | E50: 45162
A51: 10 | B51: MAO | C51: Shing-A-ling Snack: Product Innovation & Marketing Strategies | D51: 44985 | E51: 44985
A52: 11 | B52: Samahan ng Maliliit na Mangingisda ng Brgy. Gaspar Island | C52: Report Profiling | D52: 8/14, 21, & 22, 2023 | E52: 8/14, 21, & 22, 2023
C53: Community Outreach of MSC Gasan | D53: 8/30-31/2023 | E53: 8/30-31/2023
C54: Distribution of Farm Materials to Seaweed Farmers | D54: 44988 | E54: 44988
A55: 12 | B55: Samahan ng Maliliit na Mangingisda Brgy. Yook | C55: Report Profiling | D55: 8/14, 21, & 22, 2023 | E55: 8/14, 21, & 22, 2023
C56: Community Outreach of MSC Gasan | D56: 8/30-31/2023 | E56: 8/30-31/2023
C57: Distribution of Farm Materials to Seaweed Farmers | D57: 44988 | E57: 44988
A58: 13 | B58: Samahan ng Maliliit na Mangingisda Brgy.Daykitin | C58: Report Profiling | D58: 8/14, 21, & 22, 2023 | E58: 8/14, 21, & 22, 2023
C59: Community Outreach of MSC Gasan | D59: 8/30-31/2023 | E59: 8/30-31/2023
C60: Distribution of Farm Materials to Seaweed Farmers | D60: 44988 | E60: 44988
A61: 14 | B61: Samahan ng Maliliit na Mangingisda Brgy. Caballero | C61: Report Profiling | D61: 44988 | E61: 44988
C62: Community Outreach of MSC Gasan | D62: 8/30-31/2023 | E62: 8/30-31/2023
C63: Distribution of Farm Materials to Seaweed Farmers | D63: 44988 | E63: 44988
A64: 15 | B64: DepEd | C64: Capacitating Educators in Research Areas and Challenges | D64: 45269 | E64: 45269
A65: 16 | B65: DSWD | C65: Shing-A-ling Snack: Product Innovation & Marketing Strategies | D65: 44985 | E65: 44985
C66: Micro-Enterprise Development Training | D66: 44998 | E66: 44998
A67: 17 | B67: DTI | C67: Marinduque Bamboo Industry Development Council Reorganization and 1st Quarter Meeting for 2023 | D67: 45000 | E67: 45000
C68: Entrepreneurial Mind Setting and Behavior Training | D68: 45190 | E68: 45191
C69: Technology Forum and Workshop on New Trends in Agribusiness for Federation of Mogpog Association | D69: 45009 | E69: 45009
C70: Project Orientation and Strategic Planning (Arrowroot Project) | D70: 45147 | E70: 45147
A71: 18 | B71: PNP | C71: Planting Activities | D71: 45161 | E71: 45163
A72: 19 | B72: Samahan ng mga Maghihipon sa Tabionan | C72: Empowering Groups' Leadership Skills Training; Partner | D72: 45049 | E72: 45049
C73: Seminar on the Conservation and Protection of Freshwater Prawns (Macrobrachium spp.) | D73: 45070 | E73: 45070
A74: 20 | B74: DPWH | C74: Marinduque Wildlife Sanctuary - Protected Area Management Board (MWS) -PAMB Special Meeting | D74: 45069 | E74: 45069
A75: 21 | B75: Oragnization: Katiwala ng Malaking Inalang | C75: Training on Free-Range Chicken Production and Management | D75: 45091 | E75: 45092
C76: Technology Training on Free Range Chicken Production and Management | D76: 45155 | E76: 45156
C77: Free range chicken production | D77: 45227 | E77: 45227
A78: 22 | B78: University of the Philippines | C78: Meeting for the Sub-Agreement re. GMAP Marinduque | D78: 45098 | E78: 45098
C79: Training on Bamboo Propagation and Production | D79: 45134 | E79: 45134
C80: Site/Land Preparation Activities | D80: 45155 | E80: 45156
C81: Planting Activities | D81: 45161 | E81: 45163
A82: 23 | B82: TWG-WRM DENR IVB | C82: 1ST CY 2023 TWG on Resource Management Meeting cum Orientation on the Formation of Watershed Management Council (WMC) | D82: 45012 | E82: 45012
C83: Roll-out of the River Basin Integrated Information System (RBIIMS) | D83: 45013 | E83: 45014
A84: 24 | B84: DOST | C84: Meeting for the Sub-Agreement re. GMAP Marinduque | D84: 45098 | E84: 45098
C85: Capacity Building of the Protected Area Management Office- Marrinduque Wildlife Sanctuary (PAMO-MWS) PAMB Members, PAMO and TSD Staff/ Personnel | D85: 45198 | E85: 45199
C86: Native Pig Program Terminal Review Meeting | D86: 45169 | E86: 45169
A87: 25 | B87: BAFA | C87: Project Orientation and Strategic Planning (Arrowroot Project) | D87: 45147 | E87: 45147
C88: Arrowroot Plantation and Management Training | D88: 45212 | E88: 45212
C89: Processing Productin of Arrowroot Bagasse Pastries Chewy Cookies and Brownies | D89: 45254 | E89: 45254
B91: Total Number of Active Partnerships: | C91: =COUNTA(B18:B90) -> 25
A93: Prepared by:
B96: Dr. MA. EDELWINA M. BLASÉ | C96: 45348
B97: Vice President for Research, Development, Extension and Training | C97: Date
A100: Approved:
B103: Prof. DIOSDADO P. ZULUETA, DPA | C103: 45348
B104: SUC President III | C104: Date
